Workbook

Sheet DASHBOARD
A1: ANTHONY COMMUNITY MEDIA - BUSINESS DATABASE
A2: Anthony Village & Maryland / Mende catchments | 18-category taxonomy | Last refreshed 2026-09-16
A4: HEADLINE NUMBERS
A5: Total businesses in database | C5: =COUNTA('MASTER DATABASE'!B2:B931) -> 930
A6: Anthony / Anthony Village | C6: =COUNTIF('MASTER DATABASE'!C2:C931,"Anthony / Anthony Village") -> 478
A7: Maryland / Mende | C7: =COUNTIF('MASTER DATABASE'!C2:C931,"Maryland / Mende") -> 452
A8: With a phone number | C8: =COUNTIF('MASTER DATABASE'!M2:M931,"Yes") -> 559
A9: Google-verified location | C9: =COUNTIF('MASTER DATABASE'!S2:S931,"Google-verified") -> 724
A10: Priority A prospects | C10: =COUNTIF('MASTER DATABASE'!T2:T931,"A - High commercial relevance") -> 152
A11: Priority B prospects | C11: =COUNTIF('MASTER DATABASE'!T2:T931,"B - Potential advertiser") -> 407
A13: Target range (client brief) | C13: 700 - 1,000+
A14: Coverage vs. 700 minimum | C14: =C5/700 -> 1.3285714
A16: BUSINESSES BY CATEGORY
A17: Category | B17: Anthony / Anthony Village | C17: Maryland / Mende | D17: Total | E17: Priority A | F17: % of database
A18: Restaurants | B18: =COUNTIFS('MASTER DATABASE'!C2:C931,$B$17,'MASTER DATABASE'!E2:E931,$A18) -> 34 | C18: =COUNTIFS('MASTER DATABASE'!C2:C931,$C$17,'MASTER DATABASE'!E2:E931,$A18) -> 63 | D18: =SUM(B18:C18) -> 97 | E18: =COUNTIFS('MASTER DATABASE'!E2:E931,$A18,'MASTER DATABASE'!T2:T931,"A - High commercial relevance") -> 7 | F18: =IFERROR(D18/$D$36,0) -> 0.10430108
A19: Hotels | B19: =COUNTIFS('MASTER DATABASE'!C2:C931,$B$17,'MASTER DATABASE'!E2:E931,$A19) -> 11 | C19: =COUNTIFS('MASTER DATABASE'!C2:C931,$C$17,'MASTER DATABASE'!E2:E931,$A19) -> 14 | D19: =SUM(B19:C19) -> 25 | E19: =COUNTIFS('MASTER DATABASE'!E2:E931,$A19,'MASTER DATABASE'!T2:T931,"A - High commercial relevance") -> 4 | F19: =IFERROR(D19/$D$36,0) -> 0.02688172
A20: Gyms | B20: =COUNTIFS('MASTER DATABASE'!C2:C931,$B$17,'MASTER DATABASE'!E2:E931,$A20) -> 15 | C20: =COUNTIFS('MASTER DATABASE'!C2:C931,$C$17,'MASTER DATABASE'!E2:E931,$A20) -> 12 | D20: =SUM(B20:C20) -> 27 | E20: =COUNTIFS('MASTER DATABASE'!E2:E931,$A20,'MASTER DATABASE'!T2:T931,"A - High commercial relevance") -> 1 | F20: =IFERROR(D20/$D$36,0) -> 0.029032258
A21: Salons | B21: =COUNTIFS('MASTER DATABASE'!C2:C931,$B$17,'MASTER DATABASE'!E2:E931,$A21) -> 43 | C21: =COUNTIFS('MASTER DATABASE'!C2:C931,$C$17,'MASTER DATABASE'!E2:E931,$A21) -> 79 | D21: =SUM(B21:C21) -> 122 | E21: =COUNTIFS('MASTER DATABASE'!E2:E931,$A21,'MASTER DATABASE'!T2:T931,"A - High commercial relevance") -> 11 | F21: =IFERROR(D21/$D$36,0) -> 0.1311828
A22: Barbers | B22: =COUNTIFS('MASTER DATABASE'!C2:C931,$B$17,'MASTER DATABASE'!E2:E931,$A22) -> 8 | C22: =COUNTIFS('MASTER DATABASE'!C2:C931,$C$17,'MASTER DATABASE'!E2:E931,$A22) -> 10 | D22: =SUM(B22:C22) -> 18 | E22: =COUNTIFS('MASTER DATABASE'!E2:E931,$A22,'MASTER DATABASE'!T2:T931,"A - High commercial relevance") -> 1 | F22: =IFERROR(D22/$D$36,0) -> 0.019354839
A23: Medical Centres | B23: =COUNTIFS('MASTER DATABASE'!C2:C931,$B$17,'MASTER DATABASE'!E2:E931,$A23) -> 31 | C23: =COUNTIFS('MASTER DATABASE'!C2:C931,$C$17,'MASTER DATABASE'!E2:E931,$A23) -> 29 | D23: =SUM(B23:C23) -> 60 | E23: =COUNTIFS('MASTER DATABASE'!E2:E931,$A23,'MASTER DATABASE'!T2:T931,"A - High commercial relevance") -> 18 | F23: =IFERROR(D23/$D$36,0) -> 0.064516129
A24: Dentists | B24: =COUNTIFS('MASTER DATABASE'!C2:C931,$B$17,'MASTER DATABASE'!E2:E931,$A24) -> 6 | C24: =COUNTIFS('MASTER DATABASE'!C2:C931,$C$17,'MASTER DATABASE'!E2:E931,$A24) -> 3 | D24: =SUM(B24:C24) -> 9 | E24: =COUNTIFS('MASTER DATABASE'!E2:E931,$A24,'MASTER DATABASE'!T2:T931,"A - High commercial relevance") -> 3 | F24: =IFERROR(D24/$D$36,0) -> 0.0096774194
A25: Pharmacies | B25: =COUNTIFS('MASTER DATABASE'!C2:C931,$B$17,'MASTER DATABASE'!E2:E931,$A25) -> 13 | C25: =COUNTIFS('MASTER DATABASE'!C2:C931,$C$17,'MASTER DATABASE'!E2:E931,$A25) -> 24 | D25: =SUM(B25:C25) -> 37 | E25: =COUNTIFS('MASTER DATABASE'!E2:E931,$A25,'MASTER DATABASE'!T2:T931,"A - High commercial relevance") -> 5 | F25: =IFERROR(D25/$D$36,0) -> 0.039784946
A26: Schools | B26: =COUNTIFS('MASTER DATABASE'!C2:C931,$B$17,'MASTER DATABASE'!E2:E931,$A26) -> 12 | C26: =COUNTIFS('MASTER DATABASE'!C2:C931,$C$17,'MASTER DATABASE'!E2:E931,$A26) -> 21 | D26: =SUM(B26:C26) -> 33 | E26: =COUNTIFS('MASTER DATABASE'!E2:E931,$A26,'MASTER DATABASE'!T2:T931,"A - High commercial relevance") -> 1 | F26: =IFERROR(D26/$D$36,0) -> 0.035483871
A27: Churches | B27: =COUNTIFS('MASTER DATABASE'!C2:C931,$B$17,'MASTER DATABASE'!E2:E931,$A27) -> 11 | C27: =COUNTIFS('MASTER DATABASE'!C2:C931,$C$17,'MASTER DATABASE'!E2:E931,$A27) -> 14 | D27: =SUM(B27:C27) -> 25 | E27: =COUNTIFS('MASTER DATABASE'!E2:E931,$A27,'MASTER DATABASE'!T2:T931,"A - High commercial relevance") -> 3 | F27: =IFERROR(D27/$D$36,0) -> 0.02688172
A28: Supermarkets | B28: =COUNTIFS('MASTER DATABASE'!C2:C931,$B$17,'MASTER DATABASE'!E2:E931,$A28) -> 56 | C28: =COUNTIFS('MASTER DATABASE'!C2:C931,$C$17,'MASTER DATABASE'!E2:E931,$A28) -> 19 | D28: =SUM(B28:C28) -> 75 | E28: =COUNTIFS('MASTER DATABASE'!E2:E931,$A28,'MASTER DATABASE'!T2:T931,"A - High commercial relevance") -> 13 | F28: =IFERROR(D28/$D$36,0) -> 0.080645161
A29: Boutiques | B29: =COUNTIFS('MASTER DATABASE'!C2:C931,$B$17,'MASTER DATABASE'!E2:E931,$A29) -> 43 | C29: =COUNTIFS('MASTER DATABASE'!C2:C931,$C$17,'MASTER DATABASE'!E2:E931,$A29) -> 12 | D29: =SUM(B29:C29) -> 55 | E29: =COUNTIFS('MASTER DATABASE'!E2:E931,$A29,'MASTER DATABASE'!T2:T931,"A - High commercial relevance") -> 13 | F29: =IFERROR(D29/$D$36,0) -> 0.059139785
A30: Home Services | B30: =COUNTIFS('MASTER DATABASE'!C2:C931,$B$17,'MASTER DATABASE'!E2:E931,$A30) -> 41 | C30: =COUNTIFS('MASTER DATABASE'!C2:C931,$C$17,'MASTER DATABASE'!E2:E931,$A30) -> 32 | D30: =SUM(B30:C30) -> 73 | E30: =COUNTIFS('MASTER DATABASE'!E2:E931,$A30,'MASTER DATABASE'!T2:T931,"A - High commercial relevance") -> 9 | F30: =IFERROR(D30/$D$36,0) -> 0.078494624
A31: Real Estate | B31: =COUNTIFS('MASTER DATABASE'!C2:C931,$B$17,'MASTER DATABASE'!E2:E931,$A31) -> 39 | C31: =COUNTIFS('MASTER DATABASE'!C2:C931,$C$17,'MASTER DATABASE'!E2:E931,$A31) -> 28 | D31: =SUM(B31:C31) -> 67 | E31: =COUNTIFS('MASTER DATABASE'!E2:E931,$A31,'MASTER DATABASE'!T2:T931,"A - High commercial relevance") -> 15 | F31: =IFERROR(D31/$D$36,0) -> 0.072043011
A32: Professional Services | B32: =COUNTIFS('MASTER DATABASE'!C2:C931,$B$17,'MASTER DATABASE'!E2:E931,$A32) -> 63 | C32: =COUNTIFS('MASTER DATABASE'!C2:C931,$C$17,'MASTER DATABASE'!E2:E931,$A32) -> 34 | D32: =SUM(B32:C32) -> 97 | E32: =COUNTIFS('MASTER DATABASE'!E2:E931,$A32,'MASTER DATABASE'!T2:T931,"A - High commercial relevance") -> 19 | F32: =IFERROR(D32/$D$36,0) -> 0.10430108
A33: Auto Services | B33: =COUNTIFS('MASTER DATABASE'!C2:C931,$B$17,'MASTER DATABASE'!E2:E931,$A33) -> 20 | C33: =COUNTIFS('MASTER DATABASE'!C2:C931,$C$17,'MASTER DATABASE'!E2:E931,$A33) -> 13 | D33: =SUM(B33:C33) -> 33 | E33: =COUNTIFS('MASTER DATABASE'!E2:E931,$A33,'MASTER DATABASE'!T2:T931,"A - High commercial relevance") -> 6 | F33: =IFERROR(D33/$D$36,0) -> 0.035483871
A34: Event Businesses | B34: =COUNTIFS('MASTER DATABASE'!C2:C931,$B$17,'MASTER DATABASE'!E2:E931,$A34) -> 29 | C34: =COUNTIFS('MASTER DATABASE'!C2:C931,$C$17,'MASTER DATABASE'!E2:E931,$A34) -> 30 | D34: =SUM(B34:C34) -> 59 | E34: =COUNTIFS('MASTER DATABASE'!E2:E931,$A34,'MASTER DATABASE'!T2:T931,"A - High commercial relevance") -> 20 | F34: =IFERROR(D34/$D$36,0) -> 0.06344086
A35: Caterers | B35: =COUNTIFS('MASTER DATABASE'!C2:C931,$B$17,'MASTER DATABASE'!E2:E931,$A35) -> 3 | C35: =COUNTIFS('MASTER DATABASE'!C2:C931,$C$17,'MASTER DATABASE'!E2:E931,$A35) -> 15 | D35: =SUM(B35:C35) -> 18 | E35: =COUNTIFS('MASTER DATABASE'!E2:E931,$A35,'MASTER DATABASE'!T2:T931,"A - High commercial relevance") -> 3 | F35: =IFERROR(D35/$D$36,0) -> 0.019354839
A36: TOTAL | B36: =SUM(B18:B35) -> 478 | C36: =SUM(C18:C35) -> 452 | D36: =SUM(D18:D35) -> 930 | E36: =SUM(E18:E35) -> 152 | F36: =IFERROR(D36/$D$36,0) -> 1
A38: Note | B38: Every figure on this sheet is a live formula over the MASTER DATABASE tab - add or edit rows there and these update automatically.

Sheet README
A1: HOW THIS DATABASE IS BUILT
A3: Purpose | B3: A sales-ready directory of businesses in the Anthony Village and Maryland / Mende catchments for Anthony Community Media.
A4: Catchments | B4: Two only: Anthony / Anthony Village, and Maryland / Mende (which includes Onigbongbo and the Maryland Mall cluster). Legacy Ajao Estate and Araromi records have been folded into Anthony; legacy Mende records into Maryland / Mende.
A5: Geographic rule | B5: A business is assigned to a catchment by its Google coordinates first, then its street address. Anthony is centred on 6.5595 / 3.3692; Maryland on 6.5700 / 3.3685. Records beyond ~1.2 km of either centre were excluded.
A6: Category taxonomy | B6: All records are mapped onto the client's 18 categories. The original label from the source (e.g. "Beauty Salons and Spas", "Dry cleaner") is preserved in the Source Category column so nothing is lost.
A7: Deduplication | B7: Records are matched on normalised phone number, then normalised name plus street, then normalised name. Where a legacy record and a Google record describe the same business, the two are merged and the richer value kept for each field.
A8: Prospect priority | B8: A = has a phone number and either a website or 10+ Google reviews (contactable and visible). B = has a phone number. C = no contact number captured yet.
A9: What is verified | B9: "Google-verified" means the business has a live Google Maps listing with coordinates as at the date above. "Directory listing only" means it came from a directory and has not yet been confirmed on Google.
A10: Honest limitation | B10: This is a strong working base, not a claim of exhaustive coverage. Street-level canvassing will still surface unlisted businesses, especially small shops without a Google presence.
A11: How to use it | B11: Filter MASTER DATABASE by Catchment, Category and Prospect Priority to build a call list. Record outcomes in Sales Status and Sales Notes. The DASHBOARD and summary tabs recalculate from whatever is in MASTER DATABASE.

Sheet MASTER DATABASE
A1: ID | B1: Business Name | C1: Catchment | D1: Street / Cluster | E1: Category | F1: Source Category | G1: Full Address | H1: Phone | I1: Website | J1: Google Maps | K1: Google Rating | L1: Google Reviews | M1: Has Phone | N1: Latitude | O1: Longitude | P1: Data Source | Q1: Date Added | R1: Last Checked | S1: Verification | T1: Prospect Priority | U1: Suggested Package | V1: Sales Status | W1: Sales Notes
A2: 1 | B2: Akwa Imah Restaurant & Bar | C2: Anthony / Anthony Village | D2: Onigbongbo | E2: Restaurants | F2: Restaurant | G2: Onigbongbo, 14 Mobolaji Bank Anthony Way | M2: No | N2: 6.57427 | O2: 3.36322 | P2: Google Maps (verified search) | Q2: 2026-09-16 | R2: 2026-09-16 | S2: Google-verified | T2: C - Listing only (no contact yet) | U2: Listing | V2: Not Contacted
A3: 2 | B3: Alatasuesue Food Services Ltd, Purple Maryland Mall | C3: Anthony / Anthony Village | D3: 350 Ikorodu Rd | E3: Restaurants | F3: Fast Food | G3: 350 Ikorodu Rd, Anthony, Lagos 100211, Lagos | M3: No | N3: 6.56739 | O3: 3.36724 | P3: Google Maps (verified search) | Q3: 2026-09-16 | R3: 2026-09-16 | S3: Google-verified | T3: C - Listing only (no contact yet) | U3: Listing | V3: Not Contacted
A4: 3 | B4: Alubarika Foods and Agro-Allied Services | C4: Anthony / Anthony Village | D4: Apostolic Faith Church | E4: Restaurants | F4: Food Services | G4: Apostolic Faith Church, Anthony Village, Lagos | H4: +2348024878860 | M4: Yes | P4: Legacy seed (Finelib / NGEX / Cybo) | Q4: 2026-09-16 | R4: 2026-09-16 | S4: Directory listing only | T4: B - Potential advertiser | U4: Standard | V4: Not Contacted
A5: 4 | B5: Amarissa Seafood Shop | C5: Anthony / Anthony Village | D5: 3 Bola Street | E5: Restaurants | F5: Food Services | G5: 3 Bola Street, Anthony Village, Kosofe Lagos | H5: +2348023144061 | J5: https://www.google.com/maps/place/?q=place_id:ChIJzTFh8YWNOxARj40lqHNqF80 | M5: Yes | N5: 6.5607853 | O5: 3.369635 | P5: Legacy seed + Google Maps | Q5: 2026-09-16 | R5: 2026-09-16 | S5: Google-verified | T5: B - Potential advertiser | U5: Standard | V5: Not Contacted
A6: 5 | B6: Bukka Hut | C6: Anthony / Anthony Village | D6: 6 Anthony Village Rd | E6: Restaurants | F6: Food / Restaurant | G6: 6 Anthony Village Rd, Anthony, Lagos 105102 | H6: +2347000550055 | J6: https://www.google.com/maps/place/?q=place_id:ChIJu7XxIv2NOxARUbqFSQy1Z6Q | K6: 4.2 | L6: 49 | M6: Yes | N6: 6.5594616 | O6: 3.3686859 | P6: Legacy seed + Google Maps | Q6: 2026-09-16 | R6: 2026-09-16 | S6: Google-verified | T6: A - High commercial relevance | U6: Premium | V6: Not Contacted
A7: 6 | B7: Calabar Pot | C7: Anthony / Anthony Village | D7: Bungalow | E7: Restaurants | F7: African restaurant | G7: Bungalow, 10 Adebayo Mokuolu St, Anthony, Lagos 105102, Lagos, Nigeria | H7: +2348108688639 | J7: https://www.google.com/maps/place/?q=place_id:ChIJiz2COLqVOxARBLzQp_HlOjs | K7: 5 | L7: 1 | M7: Yes | N7: 6.5581386 | O7: 3.3708764 | P7: Google Maps (Apify scrape) | Q7: 2026-09-16 | R7: 2026-09-16 | S7: Google-verified | T7: B - Potential advertiser | U7: Standard | V7: Not Contacted
A8: 7 | B8: Carol’s Confectioners Ltd | C8: Anthony / Anthony Village | D8: 12 Ayanboye Street | E8: Restaurants | F8: Food Services | G8: 12 Ayanboye Street, Anthony Village, Kosofe Lagos | H8: +2348033028774 | M8: Yes | P8: Legacy seed (Finelib / NGEX / Cybo) | Q8: 2026-09-16 | R8: 2026-09-16 | S8: Directory listing only | T8: B - Potential advertiser | U8: Standard | V8: Not Contacted
A9: 8 | B9: Chalice Gardens (Bar & Restaurant) | C9: Anthony / Anthony Village | D9: 6 Olorunlogbon St | E9: Restaurants | F9: Food / Restaurant | G9: 6 Olorunlogbon St, Anthony, Lagos | H9: +2349074221080 | K9: 4 | L9: 39 | M9: Yes | P9: Legacy seed (Finelib / NGEX / Cybo) | Q9: 2026-09-16 | R9: 2026-09-16 | S9: Directory listing only | T9: A - High commercial relevance | U9: Premium | V9: Not Contacted
A10: 9 | B10: Charlice Restaurants | C10: Anthony / Anthony Village | D10: 1 Olorunlogbon St | E10: Restaurants | F10: Restaurant | G10: 1 Olorunlogbon St, Anthony, Lagos | H10: +2349057342218 | M10: Yes | P10: Legacy seed (Finelib / NGEX / Cybo) | Q10: 2026-09-16 | R10: 2026-09-16 | S10: Directory listing only | T10: B - Potential advertiser | U10: Standard | V10: Not contacted | W10: Source: Wikivoyage
A11: 10 | B11: Dornelly Foods | C11: Anthony / Anthony Village | D11: Odofin Oyero Dr | E11: Restaurants | F11: Restaurant | G11: Odofin Oyero Dr, Anthony, Lagos 105102, Lagos, Nigeria | J11: https://www.google.com/maps/place/?q=place_id:ChIJFxAb9IWNOxAR4weRI-RthPk | K11: 4.5 | L11: 2 | M11: No | N11: 6.5607097 | O11: 3.3693926 | P11: Google Maps (Apify scrape) | Q11: 2026-09-16 | R11: 2026-09-16 | S11: Google-verified | T11: C - Listing only (no contact yet) | U11: Listing | V11: Not Contacted
A12: 11 | B12: Edichart Shopping Mall | C12: Anthony / Anthony Village | D12: 54 Olorunlogbon St | E12: Restaurants | F12: Fast Food | G12: 54 Olorunlogbon St | K12: 4.2 | L12: 621 | M12: No | N12: 6.56354 | O12: 3.37019 | P12: Google Maps (verified search) | Q12: 2026-09-16 | R12: 2026-09-16 | S12: Google-verified | T12: C - Listing only (no contact yet) | U12: Listing | V12: Not Contacted
A13: 12 | B13: Fifi's Oven | C13: Anthony / Anthony Village | D13: 3 Opeifa Street | E13: Restaurants | F13: Food Services | G13: 3 Opeifa Street, Ajao Estate, Anthony Village, Ikeja Lagos | H13: +2348034078227 | I13: http://www.fifisoven.com/ | J13: https://www.google.com/maps/place/?q=place_id:ChIJrygKPXOSOxARtkiXCb7ve8o | K13: 3.7 | L13: 49 | M13: Yes | N13: 6.5605343 | O13: 3.3689203 | P13: Legacy seed + Google Maps | Q13: 2026-09-16 | R13: 2026-09-16 | S13: Google-verified | T13: A - High commercial relevance | U13: Premium | V13: Not Contacted
A14: 13 | B14: Grillz 'N' Thingz | C14: Anthony / Anthony Village | D14: 3 Adekoya Sq | E14: Restaurants | F14: Restaurant | G14: 3 Adekoya Sq | K14: 4.1 | L14: 60 | M14: No | N14: 6.56366 | O14: 3.36907 | P14: Google Maps (verified search) | Q14: 2026-09-16 | R14: 2026-09-16 | S14: Google-verified | T14: C - Listing only (no contact yet) | U14: Listing | V14: Not Contacted
A15: 14 | B15: Iya Monday | C15: Anthony / Anthony Village | D15: 7 Adebayo Mokuolu St | E15: Restaurants | F15: Restaurant | G15: 7 Adebayo Mokuolu St, Anthony, Lagos | M15: No | P15: Legacy seed (Finelib / NGEX / Cybo) | Q15: 2026-09-16 | R15: 2026-09-16 | S15: Directory listing only | T15: C - Listing only (no contact yet) | U15: Listing | V15: Not contacted | W15: Source: Wikivoyage
A16: 15 | B16: Labe-ofe Pots | C16: Anthony / Anthony Village | D16: 1 Adejobi Crescent | E16: Restaurants | F16: Food Services | G16: 1 Adejobi Crescent, Anthony Village, Ikeja, Lagos | H16: +2347010055229 | M16: Yes | P16: Legacy seed (Finelib / NGEX / Cybo) | Q16: 2026-09-16 | R16: 2026-09-16 | S16: Directory listing only | T16: B - Potential advertiser | U16: Standard | V16: Not Contacted
A17: 16 | B17: Local restaurant | C17: Anthony / Anthony Village | D17: H959+QV8 | E17: Restaurants | F17: Restaurant | G17: H959+QV8, Anthony Village Rd, Anthony, Lagos 105102, Lagos, Nigeria | J17: https://www.google.com/maps/place/?q=place_id:ChIJayDwTwCNOxARFnnvk_cgnOw | M17: No | N17: 6.5594338 | O17: 3.3697174 | P17: Google Maps (Apify scrape) | Q17: 2026-09-16 | R17: 2026-09-16 | S17: Google-verified | T17: C - Listing only (no contact yet) | U17: Listing | V17: Not Contacted
A18: 17 | B18: Mature Kitchen | C18: Anthony / Anthony Village | D18: Anthony Village Road | E18: Restaurants | F18: Restaurant | G18: Anthony Village Road, Anthony, Lagos | M18: No | P18: Legacy seed (Finelib / NGEX / Cybo) | Q18: 2026-09-16 | R18: 2026-09-16 | S18: Directory listing only | T18: C - Listing only (no contact yet) | U18: Listing | V18: Not contacted | W18: Source: OpenAlfa
A19: 18 | B19: Meal Express | C19: Anthony / Anthony Village | D19: Anthony | E19: Restaurants | F19: Restaurant | G19: Anthony, Ikeja 105102, Lagos, Nigeria | J19: https://www.google.com/maps/place/?q=place_id:ChIJ2dYKloWNOxAR1BBnIAyVZAc | M19: No | N19: 6.5600693 | O19: 3.3700498 | P19: Google Maps (Apify scrape) | Q19: 2026-09-16 | R19: 2026-09-16 | S19: Google-verified | T19: C - Listing only (no contact yet) | U19: Listing | V19: Not Contacted
A20: 19 | B20: Mount Foodji | C20: Anthony / Anthony Village | D20: No.6 Balogun Street | E20: Restaurants | F20: Food Services | G20: No.6 Balogun Street, Ajao Estate, Anthony Village, Lagos | H20: +2347041377461 | K20: 3.9 | L20: 39 | M20: Yes | N20: 6.56382 | O20: 3.37313 | P20: Legacy seed + Google Maps | Q20: 2026-09-16 | R20: 2026-09-16 | S20: Google-verified | T20: A - High commercial relevance | U20: Premium | V20: Not Contacted
A21: 20 | B21: Mr Krums | C21: Anthony / Anthony Village | D21: 2 Bamidele Adebule Street | E21: Restaurants | F21: Fast Food | G21: 2 Bamidele Adebule Street, Anthony Village, Lagos | H21: +2347086365055 | M21: Yes | P21: Legacy seed (Finelib / NGEX / Cybo) | Q21: 2026-09-16 | R21: 2026-09-16 | S21: Directory listing only | T21: B - Potential advertiser | U21: Standard | V21: Not contacted | W21: Source: Finelib
A22: 21 | B22: Mr. Mayas Refreshments | C22: Anthony / Anthony Village | D22: 17 Olorunlogbon Street | E22: Restaurants | F22: Fast Food | G22: 17 Olorunlogbon Street, Anthony Village, Lagos | H22: +2348025946708 | M22: Yes | P22: Legacy seed (Finelib / NGEX / Cybo) | Q22: 2026-09-16 | R22: 2026-09-16 | S22: Directory listing only | T22: B - Potential advertiser | U22: Standard | V22: Not contacted | W22: Source: Finelib
A23: 22 | B23: Onlytoyourtaste (Grill's & Fastfood) | C23: Anthony / Anthony Village | D23: 6 Olorunlogbon St | E23: Restaurants | F23: Restaurant | G23: 6 Olorunlogbon St, Anthony, Lagos 100232, Lagos, Nigeria | J23: https://www.google.com/maps/place/?q=place_id:ChIJb2K6o3eNOxARP3pz3Y6WshU | K23: 4.7 | L23: 3 | M23: No | N23: 6.5592574 | O23: 3.3701432 | P23: Google Maps (Apify scrape) | Q23: 2026-09-16 | R23: 2026-09-16 | S23: Google-verified | T23: C - Listing only (no contact yet) | U23: Listing | V23: Not Contacted
A24: 23 | B24: Paulina's Eatery | C24: Anthony / Anthony Village | D24: H959+C9R | E24: Restaurants | F24: Restaurant | G24: H959+C9R, Sylvia Cres, Anthony, Lagos 105102, Lagos, Nigeria | H24: +2348133185978 | J24: https://www.google.com/maps/place/?q=place_id:ChIJT-rvmo-NOxAR4fAfJBqaoh8 | K24: 3 | L24: 1 | M24: Yes | N24: 6.558616 | O24: 3.3683757 | P24: Google Maps (Apify scrape) | Q24: 2026-09-16 | R24: 2026-09-16 | S24: Google-verified | T24: B - Potential advertiser | U24: Standard | V24: Not Contacted
A25: 24 | B25: Precious Sweet bakes Confectionery in Maryland Lagos | C25: Anthony / Anthony Village | E25: Restaurants | K25: 5 | L25: 8 | M25: No | N25: 6.56366 | O25: 3.36446 | P25: Google Maps (verified search) | Q25: 2026-09-16 | R25: 2026-09-16 | S25: Google-verified | T25: C - Listing only (no contact yet) | U25: Listing | V25: Not Contacted
A26: 25 | B26: Printing | C26: Anthony / Anthony Village | D26: Adebayo Mokuolu St | E26: Restaurants | F26: Desktop publishing service | G26: Adebayo Mokuolu St, Anthony, Ikeja 105102, Lagos, Nigeria | J26: https://www.google.com/maps/place/?q=place_id:ChIJRUnLBwqNOxARu-zXxea_vMY | K26: 5 | L26: 1 | M26: No | N26: 6.5574658 | O26: 3.370496 | P26: Google Maps (Apify scrape) | Q26: 2026-09-16 | R26: 2026-09-16 | S26: Google-verified | T26: C - Listing only (no contact yet) | U26: Listing | V26: Not Contacted
A27: 26 | B27: Purple Spoon Shawarma | C27: Anthony / Anthony Village | D27: 15 Adebayo Mokuolu St | E27: Restaurants | F27: Restaurant | G27: 15 Adebayo Mokuolu St, Anthony, Lagos | H27: +2348089017223 | J27: https://www.google.com/maps/place/?q=place_id:ChIJu4RZHIWNOxARo1q3tuxxYHE | K27: 4 | L27: 2 | M27: Yes | N27: 6.5592321 | O27: 3.369412 | P27: Legacy seed + Google Maps | Q27: 2026-09-16 | R27: 2026-09-16 | S27: Google-verified | T27: B - Potential advertiser | U27: Standard | V27: Not contacted | W27: Source: Wikivoyage
A28: 27 | B28: Shawarma & Ice Cream | C28: Anthony / Anthony Village | D28: 10 Anthony Village Rd | E28: Restaurants | F28: Ice cream shop | G28: 10 Anthony Village Rd, Anthony, Ikeja 105102, Lagos, Nigeria | H28: +2348034075919 | J28: https://www.google.com/maps/place/?q=place_id:ChIJuTUugYWNOxAR6qpN0LGG9r0 | M28: Yes | N28: 6.559453 | O28: 3.3693809 | P28: Google Maps (Apify scrape) | Q28: 2026-09-16 | R28: 2026-09-16 | S28: Google-verified | T28: B - Potential advertiser | U28: Standard | V28: Not Contacted
A29: 28 | B29: Shedu Chops | C29: Anthony / Anthony Village | D29: 16 Adebayo Mokuolu Street | E29: Restaurants | F29: Fast Food | G29: 16 Adebayo Mokuolu Street, Anthony Village, Lagos | H29: +2347016737277 | J29: https://www.google.com/maps/place/?q=place_id:ChIJUZZTe-uNOxARrLn_9x36e7c | K29: 4.8 | L29: 15 | M29: Yes | N29: 6.5600695 | O29: 3.3714821 | P29: Legacy seed + Google Maps | Q29: 2026-09-16 | R29: 2026-09-16 | S29: Google-verified | T29: A - High commercial relevance | U29: Premium | V29: Not contacted | W29: Source: Finelib
A30: 29 | B30: SNACKIT | C30: Anthony / Anthony Village | D30: 10 Anthony Village Rd | E30: Restaurants | F30: Food court | G30: 10 Anthony Village Rd, Anthony, Lagos 105102, Lagos, Nigeria | J30: https://www.google.com/maps/place/?q=place_id:ChIJY-AOq5uNOxARL9gfqVP0Z78 | M30: No | N30: 6.559453 | O30: 3.3693809 | P30: Google Maps (Apify scrape) | Q30: 2026-09-16 | R30: 2026-09-16 | S30: Google-verified | T30: C - Listing only (no contact yet) | U30: Listing | V30: Not Contacted
A31: 30 | B31: Taj Mahal Restaurant | C31: Anthony / Anthony Village | D31: 10 Mobolaji Bank Anthony Way | E31: Restaurants | F31: Restaurant | G31: 10 Mobolaji Bank Anthony Way | K31: 5 | L31: 1 | M31: No | N31: 6.57254 | O31: 3.3639 | P31: Google Maps (verified search) | Q31: 2026-09-16 | R31: 2026-09-16 | S31: Google-verified | T31: C - Listing only (no contact yet) | U31: Listing | V31: Not Contacted
A32: 31 | B32: Toptaste Food and Soups | C32: Anthony / Anthony Village | D32: 41 Olorunlogbon Street | E32: Restaurants | F32: Food Services | G32: 41 Olorunlogbon Street, Anthony Village, Lagos | H32: +2348099990846 | M32: Yes | P32: Legacy seed (Finelib / NGEX / Cybo) | Q32: 2026-09-16 | R32: 2026-09-16 | S32: Directory listing only | T32: B - Potential advertiser | U32: Standard | V32: Not Contacted
A33: 32 | B33: Yakoyo Food Canteen | C33: Anthony / Anthony Village | D33: 2 Odunlami St | E33: Restaurants | F33: Restaurant | G33: 2 Odunlami St, Anthony, Lagos | J33: https://www.google.com/maps/place/?q=place_id:ChIJpwjpk92NOxAR2KTajENQSAU | K33: 5 | L33: 3 | M33: No | N33: 6.5595707 | O33: 3.3696572 | P33: Legacy seed + Google Maps | Q33: 2026-09-16 | R33: 2026-09-16 | S33: Google-verified | T33: C - Listing only (no contact yet) | U33: Listing | V33: Not contacted | W33: Source: Wikivoyage
A34: 33 | B34: Zakari Umar | C34: Anthony / Anthony Village | D34: 16 Anthony Village Rd | E34: Restaurants | F34: Fast food restaurant | G34: 16 Anthony Village Rd, Anthony, Lagos 105102, Lagos, Nigeria | J34: https://www.google.com/maps/place/?q=place_id:ChIJlwoXgpeNOxARLpTvwUOLmcY | M34: No | N34: 6.5594134 | O34: 3.3698488 | P34: Google Maps (Apify scrape) | Q34: 2026-09-16 | R34: 2026-09-16 | S34: Google-verified | T34: C - Listing only (no contact yet) | U34: Listing | V34: Not Contacted
A35: 34 | B35: Zhukkii's Delights Soups And Food | C35: Anthony / Anthony Village | D35: 126c Sylvia Cres | E35: Restaurants | F35: Restaurant | G35: 126c Sylvia Cres, beside Zenith Bank, Anthony, Lagos 105102, Lagos, Nigeria | H35: +2348189509029 | J35: https://www.google.com/maps/place/?q=place_id:ChIJf5zavZSNOxARJUJL0ehlJ6A | M35: Yes | N35: 6.5593901 | O35: 3.3682047 | P35: Google Maps (Apify scrape) | Q35: 2026-09-16 | R35: 2026-09-16 | S35: Google-verified | T35: B - Potential advertiser | U35: Standard | V35: Not Contacted
A36: 35 | B36: Abramovich Hotels and Suites | C36: Anthony / Anthony Village | D36: 2 Sanni Lane | E36: Hotels | F36: Hotels | G36: 2 Sanni Lane, Anthony Village, Lagos | H36: +2349154661572 | M36: Yes | P36: Legacy seed (Finelib / NGEX / Cybo) | Q36: 2026-09-16 | R36: 2026-09-16 | S36: Directory listing only | T36: B - Potential advertiser | U36: Standard | V36: Not Contacted
A37: 36 | B37: Banex Hotel And Suites | C37: Anthony / Anthony Village | E37: Hotels | K37: 3.5 | L37: 99 | M37: No | N37: 6.56427 | O37: 3.37034 | P37: Google Maps (verified search) | Q37: 2026-09-16 | R37: 2026-09-16 | S37: Google-verified | T37: C - Listing only (no contact yet) | U37: Listing | V37: Not Contacted
A38: 37 | B38: Diamond Hotel | C38: Anthony / Anthony Village | D38: 5 Okunfolami Street | E38: Hotels | F38: Hotels | G38: 5 Okunfolami Street, Anthony Village, Ikeja | H38: +23417920514 | K38: 3.8 | L38: 421 | M38: Yes | N38: 6.56571 | O38: 3.37141 | P38: Legacy seed + Google Maps | Q38: 2026-09-16 | R38: 2026-09-16 | S38: Google-verified | T38: A - High commercial relevance | U38: Premium | V38: Not Contacted
A39: 38 | B39: Hotel Newcastle | C39: Anthony / Anthony Village | D39: Plot 11 Adebayo Mokuolu Street | E39: Hotels | F39: Hotels | G39: Plot 11 Adebayo Mokuolu Street, Anthony Village, Ikeja Lagos | H39: +2341764666001 | M39: Yes | P39: Legacy seed (Finelib / NGEX / Cybo) | Q39: 2026-09-16 | R39: 2026-09-16 | S39: Directory listing only | T39: B - Potential advertiser | U39: Standard | V39: Not Contacted
A40: 39 | B40: Ivory Exclusive Hotel & Suites | C40: Anthony / Anthony Village | D40: 60 Olorunlogbon Street | E40: Hotels | F40: Hotels | G40: 60 Olorunlogbon Street, Anthony Village, Lagos | H40: +2347087355551 | M40: Yes | P40: Legacy seed (Finelib / NGEX / Cybo) | Q40: 2026-09-16 | R40: 2026-09-16 | S40: Directory listing only | T40: B - Potential advertiser | U40: Standard | V40: Not Contacted
A41: 40 | B41: Maryland Military Barracks Gate 1 | C41: Anthony / Anthony Village | D41: Mobolaji Bank Anthony Way | E41: Hotels | F41: Hostel | G41: Mobolaji Bank Anthony Way | K41: 4.3 | L41: 188 | M41: No | N41: 6.57108 | O41: 3.36229 | P41: Google Maps (verified search) | Q41: 2026-09-16 | R41: 2026-09-16 | S41: Google-verified | T41: C - Listing only (no contact yet) | U41: Listing | V41: Not Contacted
A42: 41 | B42: Pholax Hotel & Suites | C42: Anthony / Anthony Village | E42: Hotels | K42: 4 | L42: 1088 | M42: No | N42: 6.56421 | O42: 3.37031 | P42: Google Maps (verified search) | Q42: 2026-09-16 | R42: 2026-09-16 | S42: Google-verified | T42: C - Listing only (no contact yet) | U42: Listing | V42: Not Contacted
A43: 42 | B43: Prince Of Anthony Hotel | C43: Anthony / Anthony Village | D43: 27 Oyedele Ogunniyi Street | E43: Hotels | F43: Hotels | G43: 27 Oyedele Ogunniyi Street, Anthony Village, Ikeja | H43: +2348134050925 | M43: Yes | P43: Legacy seed (Finelib / NGEX / Cybo) | Q43: 2026-09-16 | R43: 2026-09-16 | S43: Directory listing only | T43: B - Potential advertiser | U43: Standard | V43: Not Contacted
A44: 43 | B44: Queen Idia Hotel | C44: Anthony / Anthony Village | D44: 11 Sylvia Crescent | E44: Hotels | F44: Hotels | G44: 11 Sylvia Crescent, Anthony Village, Lagos | H44: +2349031719594 | M44: Yes | P44: Legacy seed (Finelib / NGEX / Cybo) | Q44: 2026-09-16 | R44: 2026-09-16 | S44: Directory listing only | T44: B - Potential advertiser | U44: Standard | V44: Not Contacted
A45: 44 | B45: StayCation Suites & Apartment | C45: Anthony / Anthony Village | D45: 12A Bode Peters Street | E45: Hotels | F45: Hotels | G45: 12A Bode Peters Street, Anthony Village, Lagos | H45: +2348176576963 | K45: 3.9 | L45: 136 | M45: Yes | N45: 6.56183 | O45: 3.37357 | P45: Legacy seed + Google Maps | Q45: 2026-09-16 | R45: 2026-09-16 | S45: Google-verified | T45: A - High commercial relevance | U45: Premium | V45: Not Contacted
A46: 45 | B46: Sylva Link Hotel Limited | C46: Anthony / Anthony Village | D46: 1 Kunle Adebowale Street | E46: Hotels | F46: Hotels | G46: 1 Kunle Adebowale Street, Off Adebayo Mokuolu Street, Anthony Village, Lagos | H46: +2348032213140 | M46: Yes | P46: Legacy seed (Finelib / NGEX / Cybo) | Q46: 2026-09-16 | R46: 2026-09-16 | S46: Directory listing only | T46: B - Potential advertiser | U46: Standard | V46: Not Contacted
A47: 46 | B47: Anthony Village Recreation Center | C47: Anthony / Anthony Village | D47: Adebayo Mokuolu St | E47: Gyms | F47: Sports / Recreation | G47: Adebayo Mokuolu St, Anthony Village, Lagos 105102 | K47: 3.9 | L47: 504 | M47: No | N47: 6.56131 | O47: 3.3716 | P47: Legacy seed + Google Maps | Q47: 2026-09-16 | R47: 2026-09-16 | S47: Google-verified | T47: C - Listing only (no contact yet) | U47: Listing | V47: Not Contacted
A48: 47 | B48: Box2door Logistics | C48: Anthony / Anthony Village | D48: 4 Ayanboye Street | E48: Gyms | F48: Transportation | G48: 4 Ayanboye Street, Anthony Village, Lagos | H48: +2349032490736 | M48: Yes | P48: Legacy seed (Finelib / NGEX / Cybo) | Q48: 2026-09-16 | R48: 2026-09-16 | S48: Directory listing only | T48: B - Potential advertiser | U48: Standard | V48: Not Contacted
A49: 48 | B49: Goldcard Spa and Fitness Centre | C49: Anthony / Anthony Village | D49: 2 Yusuf okunade close | E49: Gyms | F49: Fitness center | G49: 2 Yusuf okunade close, Idiroko Est | K49: 4.6 | L49: 55 | M49: No | N49: 6.56357 | O49: 3.36478 | P49: Google Maps (verified search) | Q49: 2026-09-16 | R49: 2026-09-16 | S49: Google-verified | T49: C - Listing only (no contact yet) | U49: Listing | V49: Not Contacted
A50: 49 | B50: Gym Depot Nigeria Limited | C50: Anthony / Anthony Village | D50: 8B Faramobi Ajike | E50: Gyms | F50: Sports and Fitness | G50: 8B Faramobi Ajike, Anthony Village, Kosofe Lagos | H50: +2348033664511 | J50: https://www.google.com/maps/place/?q=place_id:ChIJK0ANgoWNOxARTTrq--gPQsk | K50: 4.6 | L50: 8 | M50: Yes | N50: 6.5594151 | O50: 3.369209 | P50: Legacy seed + Google Maps | Q50: 2026-09-16 | R50: 2026-09-16 | S50: Google-verified | T50: B - Potential advertiser | U50: Standard | V50: Not Contacted
A51: 50 | B51: i-Fitness Gym Maryland | C51: Anthony / Anthony Village | D51: 350-360 Ikorodu Rd | E51: Gyms | F51: Sports / Fitness | G51: 350-360 Ikorodu Rd, Anthony, Lagos 105102 | K51: 4.3 | L51: 3 | M51: No | N51: 6.56764 | O51: 3.36737 | P51: Legacy seed + Google Maps | Q51: 2026-09-16 | R51: 2026-09-16 | S51: Google-verified | T51: C - Listing only (no contact yet) | U51: Listing | V51: Not contacted | W51: Google/local result
A52: 51 | B52: INTERNATIONAL SPORTS INSTITUTE. | C52: Anthony / Anthony Village | D52: 11 Oseni St | E52: Gyms | F52: Sports school | G52: 11 Oseni St, Anthony, Lagos 105102, Lagos, Nigeria | I52: http://isipro.org/ | J52: https://www.google.com/maps/place/?q=place_id:ChIJH_RgZIWNOxARykBcTDCwM5c | M52: No | N52: 6.5584713 | O52: 3.3695743 | P52: Google Maps (Apify scrape) | Q52: 2026-09-16 | R52: 2026-09-16 | S52: Google-verified | T52: C - Listing only (no contact yet) | U52: Listing | V52: Not Contacted
A53: 52 | B53: M & Q Fitness And Wellness Centre | C53: Anthony / Anthony Village | D53: 53A Adediran Ajao Crescent | E53: Gyms | F53: Sports and Fitness | G53: 53A Adediran Ajao Crescent, Ajao Estate, Anthony Village, Ikeja Lagos | H53: +2348027339122 | J53: https://www.google.com/maps/place/?q=place_id:ChIJf9enoYGNOxARjM2mS-RVOuw | K53: 4.5 | L53: 91 | M53: Yes | N53: 6.5631114 | O53: 3.376756 | P53: Legacy seed + Google Maps | Q53: 2026-09-16 | R53: 2026-09-16 | S53: Google-verified | T53: A - High commercial relevance | U53: Premium | V53: Not Contacted
A54: 53 | B54: MADOKA YOGA WELLBEING INITIATIVE | C54: Anthony / Anthony Village | D54: 27 Olorunlogbon St | E54: Gyms | F54: Yoga studio | G54: 27 Olorunlogbon St | K54: 4.7 | L54: 35 | M54: No | N54: 6.5609 | O54: 3.37003 | P54: Google Maps (verified search) | Q54: 2026-09-16 | R54: 2026-09-16 | S54: Google-verified | T54: C - Listing only (no contact yet) | U54: Listing | V54: Not Contacted
A55: 54 | B55: Mediterranean Spas and Swimming Pools Ltd | C55: Anthony / Anthony Village | D55: Ground Floor | E55: Gyms | F55: Swimming pool contractor | G55: Ground Floor, Theodolite House, 306 Ikorodu Rd, Anthony, Lagos 105102, Lagos, Nigeria | H55: +2348023116254 | J55: https://www.google.com/maps/place/?q=place_id:ChIJcxsVxEyNOxARg4aQlMWMh7g | K55: 4.5 | L55: 2 | M55: Yes | N55: 6.5593888 | O55: 3.3671534 | P55: Google Maps (Apify scrape) | Q55: 2026-09-16 | R55: 2026-09-16 | S55: Google-verified | T55: B - Potential advertiser | U55: Standard | V55: Not Contacted
A56: 55 | B56: Moov Africa | C56: Anthony / Anthony Village | D56: 48 Oyedele Ogunniyi Street | E56: Gyms | F56: Transportation | G56: 48 Oyedele Ogunniyi Street, Anthony Village, Lagos | H56: +2349132000666 | M56: Yes | P56: Legacy seed (Finelib / NGEX / Cybo) | Q56: 2026-09-16 | R56: 2026-09-16 | S56: Directory listing only | T56: B - Potential advertiser | U56: Standard | V56: Not Contacted
A57: 56 | B57: Multi-Scope Investment Limited | C57: Anthony / Anthony Village | D57: 1b Yahya Close | E57: Gyms | F57: Transportation | G57: 1b Yahya Close, Off Adejobi Crescent, Anthony Village, Lagos | H57: +2348033029162 | M57: Yes | P57: Legacy seed (Finelib / NGEX / Cybo) | Q57: 2026-09-16 | R57: 2026-09-16 | S57: Directory listing only | T57: B - Potential advertiser | U57: Standard | V57: Not Contacted
A58: 57 | B58: Nigeria Health Finder | C58: Anthony / Anthony Village | D58: 711 Road | E58: Gyms | F58: Fitness center | G58: 711 Road, C close, House 2. Festac, Lagos state, Lagos 101233, Lagos, Nigeria | H58: +2347068092052 | J58: https://www.google.com/maps/place/?q=place_id:ChIJPcKgcIWNOxARFIswrB3JYqI | K58: 5 | L58: 1 | M58: Yes | N58: 6.55867 | O58: 3.3697605 | P58: Google Maps (Apify scrape) | Q58: 2026-09-16 | R58: 2026-09-16 | S58: Google-verified | T58: B - Potential advertiser | U58: Standard | V58: Not Contacted
A59: 58 | B59: Royal Chantelle | C59: Anthony / Anthony Village | D59: 126A Sylvia Crescent | E59: Gyms | F59: Transportation | G59: 126A Sylvia Crescent, Off Ikorodu Road, Anthony Village, Lagos | H59: +2348056260672 | M59: Yes | P59: Legacy seed (Finelib / NGEX / Cybo) | Q59: 2026-09-16 | R59: 2026-09-16 | S59: Directory listing only | T59: B - Potential advertiser | U59: Standard | V59: Not Contacted
A60: 59 | B60: Talod Ocean Freight Limited | C60: Anthony / Anthony Village | D60: 57 Adebayo Mokuolu Street | E60: Gyms | F60: Transportation | G60: 57 Adebayo Mokuolu Street, Anthony Village, Ikeja | H60: +2348033065472 | M60: Yes | P60: Legacy seed (Finelib / NGEX / Cybo) | Q60: 2026-09-16 | R60: 2026-09-16 | S60: Directory listing only | T60: B - Potential advertiser | U60: Standard | V60: Not Contacted
A61: 60 | B61: Tropical Arctic Logistics Ltd | C61: Anthony / Anthony Village | D61: 72 Olorunlogbon Street | E61: Gyms | F61: Transportation | G61: 72 Olorunlogbon Street, Anthony Village, Lagos | H61: +2341870906701 | M61: Yes | P61: Legacy seed (Finelib / NGEX / Cybo) | Q61: 2026-09-16 | R61: 2026-09-16 | S61: Directory listing only | T61: B - Potential advertiser | U61: Standard | V61: Not Contacted
A62: 61 | B62: Adeola Beauty Salon | C62: Anthony / Anthony Village | D62: Anthony Village | E62: Salons | F62: Beauty salon | G62: Anthony Village, 26 Olorunlogbon St | M62: No | N62: 6.56059 | O62: 3.37026 | P62: Google Maps (verified search) | Q62: 2026-09-16 | R62: 2026-09-16 | S62: Google-verified | T62: C - Listing only (no contact yet) | U62: Listing | V62: Not Contacted
A63: 62 | B63: Avi BeautySmith | C63: Anthony / Anthony Village | D63: 2 Idowu Ajao St | E63: Salons | F63: Beauty / Salon | G63: 2 Idowu Ajao St, Anthony Village, Lagos 100232 | H63: +2347011038068 | K63: 4.5 | L63: 2 | M63: Yes | N63: 6.56451 | O63: 3.37669 | P63: Legacy seed + Google Maps | Q63: 2026-09-16 | R63: 2026-09-16 | S63: Google-verified | T63: B - Potential advertiser | U63: Standard | V63: Not contacted | W63: Google/local result
A64: 63 | B64: BEAUTIPLY INTERNATIONAL | C64: Anthony / Anthony Village | D64: 2 LAGOS Mobolaji Bank Anthony Way | E64: Salons | F64: Hair salon | G64: 2 LAGOS Mobolaji Bank Anthony Way | M64: No | N64: 6.57172 | O64: 3.36687 | P64: Google Maps (verified search) | Q64: 2026-09-16 | R64: 2026-09-16 | S64: Google-verified | T64: C - Listing only (no contact yet) | U64: Listing | V64: Not Contacted
A65: 64 | B65: Beauvonne | C65: Anthony / Anthony Village | D65: 40 Oyedele Ogunniyi Street | E65: Salons | F65: Beauty Salons and Spas | G65: 40 Oyedele Ogunniyi Street, Anthony Village, Lagos | H65: +2347011635801 | K65: 4.5 | L65: 24 | M65: Yes | N65: 6.56282 | O65: 3.37091 | P65: Legacy seed + Google Maps | Q65: 2026-09-16 | R65: 2026-09-16 | S65: Google-verified | T65: A - High commercial relevance | U65: Premium | V65: Not Contacted
A66: 65 | B66: Bimfem Natural Hair Salon | C66: Anthony / Anthony Village | D66: 7 Anthony Village Rd | E66: Salons | F66: Beauty / Salon | G66: 7 Anthony Village Rd, Anthony, Lagos 100232 | H66: +2347032378915 | I66: http://www.bimfemplus.com/ | J66: https://www.google.com/maps/place/?q=place_id:ChIJ8U0FXqiROxAR01uM8Fhsuto | K66: 4.2 | L66: 26 | M66: Yes | N66: 6.5590956 | O66: 3.3690228 | P66: Legacy seed + Google Maps | Q66: 2026-09-16 | R66: 2026-09-16 | S66: Google-verified | T66: A - High commercial relevance | U66: Premium | V66: Not contacted | W66: Google/local result
A67: 66 | B67: Blessing Beauty Salon | C67: Anthony / Anthony Village | D67: 2 Oseni St | E67: Salons | F67: Hair salon | G67: 2 Oseni St, Anthony, Lagos 100232, Lagos, Nigeria | H67: +2347057003780 | J67: https://www.google.com/maps/place/?q=place_id:ChIJ00b0O9-NOxARWqvJkUyTxuY | M67: Yes | N67: 6.5588958 | O67: 3.3691193 | P67: Google Maps (Apify scrape) | Q67: 2026-09-16 | R67: 2026-09-16 | S67: Google-verified | T67: B - Potential advertiser | U67: Standard | V67: Not Contacted
A68: 67 | B68: Bukkies Signature Salon | C68: Anthony / Anthony Village | D68: 24 Oseni Street | E68: Salons | F68: Beauty Salons and Spas | G68: 24 Oseni Street, Anthony Village, Shomolu Lagos | H68: +2348034360209 | M68: Yes | P68: Legacy seed (Finelib / NGEX / Cybo) | Q68: 2026-09-16 | R68: 2026-09-16 | S68: Directory listing only | T68: B - Potential advertiser | U68: Standard | V68: Not Contacted
A69: 68 | B69: Chreg's Beauty Salon | C69: Anthony / Anthony Village | D69: 3 Oyedele Ogunniyi Street | E69: Salons | F69: Beauty Salons and Spas | G69: 3 Oyedele Ogunniyi Street, behind St. Augustine's Anglican Church, Anthony Village, Lagos | H69: +2348038505421 | M69: Yes | P69: Legacy seed (Finelib / NGEX / Cybo) | Q69: 2026-09-16 | R69: 2026-09-16 | S69: Directory listing only | T69: B - Potential advertiser | U69: Standard | V69: Not Contacted
A70: 69 | B70: D D Vision Beauty Saloon | C70: Anthony / Anthony Village | D70: 24 Anthony Village Rd | E70: Salons | F70: Beauty salon | G70: 24 Anthony Village Rd, Anthony, Lagos 100232, Lagos, Nigeria | H70: +2348153002051 | J70: https://www.google.com/maps/place/?q=place_id:ChIJ93Wig4WNOxARwb9H-4jgI2c | M70: Yes | N70: 6.5591754 | O70: 3.3693708 | P70: Google Maps (Apify scrape) | Q70: 2026-09-16 | R70: 2026-09-16 | S70: Google-verified | T70: B - Potential advertiser | U70: Standard | V70: Not Contacted
A71: 70 | B71: Deeza Beauty Shop | C71: Anthony / Anthony Village | D71: 12 Thomas Laniyan Street | E71: Salons | F71: Beauty Salons and Spas | G71: 12 Thomas Laniyan Street, Idiroko B/Stop, Anthony Village Ikeja, Lagos | H71: +2348033228414 | M71: Yes | P71: Legacy seed (Finelib / NGEX / Cybo) | Q71: 2026-09-16 | R71: 2026-09-16 | S71: Directory listing only | T71: B - Potential advertiser | U71: Standard | V71: Not Contacted
A72: 71 | B72: Demi beauty shop | C72: Anthony / Anthony Village | D72: 36 Ikorodu Rd | E72: Salons | F72: Beauty salon | G72: 36 Ikorodu Rd, mile12, Lagos 300001, Lagos, Nigeria | H72: +2348020706476 | J72: https://www.google.com/maps/place/?q=place_id:ChIJG6aZx4-NOxARkAk--7V9F-E | K72: 5 | L72: 1 | M72: Yes | N72: 6.557684 | O72: 3.367361 | P72: Google Maps (Apify scrape) | Q72: 2026-09-16 | R72: 2026-09-16 | S72: Google-verified | T72: B - Potential advertiser | U72: Standard | V72: Not Contacted
A73: 72 | B73: Dessynails Studio | C73: Anthony / Anthony Village | D73: 45 Oyedele Ogunniyi Street | E73: Salons | F73: Beauty Salons and Spas | G73: 45 Oyedele Ogunniyi Street, Anthony Village, Lagos | H73: +2349031831903 | M73: Yes | P73: Legacy seed (Finelib / NGEX / Cybo) | Q73: 2026-09-16 | R73: 2026-09-16 | S73: Directory listing only | T73: B - Potential advertiser | U73: Standard | V73: Not Contacted
A74: 73 | B74: Divaray beauty Line | C74: Anthony / Anthony Village | D74: 6 Odofin Oyero Dr | E74: Salons | F74: Beauty salon | G74: 6 Odofin Oyero Dr, Anthony, Lagos 105102, Lagos, Nigeria | J74: https://www.google.com/maps/place/?q=place_id:ChIJ50iVXgCNOxARBa47HxVbm20 | K74: 5 | L74: 1 | M74: No | N74: 6.5598407 | O74: 3.3697345 | P74: Google Maps (Apify scrape) | Q74: 2026-09-16 | R74: 2026-09-16 | S74: Google-verified | T74: C - Listing only (no contact yet) | U74: Listing | V74: Not Contacted
A75: 74 | B75: DLM Studio | C75: Anthony / Anthony Village | D75: 1A Thomas Laniyan St | E75: Salons | F75: Beauty / Hair | G75: 1A Thomas Laniyan St, Anthony Village 100232, Lagos | H75: +2348033297168 | I75: divinelooksng.com | M75: Yes | P75: Legacy seed (Finelib / NGEX / Cybo) | Q75: 2026-09-16 | R75: 2026-09-16 | S75: Directory listing only | T75: A - High commercial relevance | U75: Premium | V75: Not Contacted
A76: 75 | B76: Eliana'elio Perfume Store | C76: Anthony / Anthony Village | D76: 21 Olorunlogbon street Anthony Village Lagos | E76: Salons | F76: Cosmetics store | G76: 21 Olorunlogbon street Anthony Village Lagos, Anthony, Village 100001, Lagos, Nigeria | H76: +2348029299178 | J76: https://www.google.com/maps/place/?q=place_id:ChIJiSliTAeNOxARialrAEAXwL4 | M76: Yes | N76: 6.5603042 | O76: 3.3700472 | P76: Google Maps (Apify scrape) | Q76: 2026-09-16 | R76: 2026-09-16 | S76: Google-verified | T76: B - Potential advertiser | U76: Standard | V76: Not Contacted
A77: 76 | B77: Favour Beauty Salon | C77: Anthony / Anthony Village | D77: Adediran Ajao Cres | E77: Salons | F77: Beauty / Salon | G77: Adediran Ajao Cres, Anthony, Lagos 105102 | H77: +2348151160872 | K77: 5 | L77: 1 | M77: Yes | N77: 6.56558 | O77: 3.37563 | P77: Legacy seed + Google Maps | Q77: 2026-09-16 | R77: 2026-09-16 | S77: Google-verified | T77: B - Potential advertiser | U77: Standard | V77: Not contacted | W77: Google/local result
A78: 77 | B78: Funmi Beauty Salon | C78: Anthony / Anthony Village | D78: Anthony Village | E78: Salons | F78: Hair salon | G78: Anthony Village, 16 Olorunlogbon St, Lagos, Nigeria | H78: +2348033074266 | J78: https://www.google.com/maps/place/?q=place_id:ChIJMaKpl4WNOxARzKmGNfyu6Ys | M78: Yes | N78: 6.5598952 | O78: 3.3700474 | P78: Google Maps (Apify scrape) | Q78: 2026-09-16 | R78: 2026-09-16 | S78: Google-verified | T78: B - Potential advertiser | U78: Standard | V78: Not Contacted
A79: 78 | B79: Ginny Beauty Salon | C79: Anthony / Anthony Village | D79: 16 Olorunlogbon St | E79: Salons | F79: Beauty salon | G79: 16 Olorunlogbon St, Anthony, Lagos 105102, Lagos, Nigeria | J79: https://www.google.com/maps/place/?q=place_id:ChIJAWb8loWNOxAROeqHgUQHGy4 | M79: No | N79: 6.5598952 | O79: 3.3700474 | P79: Google Maps (Apify scrape) | Q79: 2026-09-16 | R79: 2026-09-16 | S79: Google-verified | T79: C - Listing only (no contact yet) | U79: Listing | V79: Not Contacted
A80: 79 | B80: Glowtitude | C80: Anthony / Anthony Village | D80: 54 Olorunlogbon Street | E80: Salons | F80: Beauty Salons and Spas | G80: 54 Olorunlogbon Street, Anthony Village, Lagos | H80: +2348187969047 | M80: Yes | P80: Legacy seed (Finelib / NGEX / Cybo) | Q80: 2026-09-16 | R80: 2026-09-16 | S80: Directory listing only | T80: B - Potential advertiser | U80: Standard | V80: Not Contacted
A81: 80 | B81: Hairifichairs.ng best hair vendor in Maryland | C81: Anthony / Anthony Village | D81: 60 Olorunlogbon St | E81: Salons | F81: Hairdresser | G81: 60 Olorunlogbon St | K81: 5 | L81: 6 | M81: No | N81: 6.56436 | O81: 3.3704 | P81: Google Maps (verified search) | Q81: 2026-09-16 | R81: 2026-09-16 | S81: Google-verified | T81: C - Listing only (no contact yet) | U81: Listing | V81: Not Contacted
A82: 81 | B82: HOB1705 Salon | C82: Anthony / Anthony Village | D82: 3 Sunmola Street | E82: Salons | F82: Beauty / Salon | G82: 3 Sunmola Street, Anthony, Lagos 105102 | H82: +2347039131764 | K82: 4.6 | L82: 22 | M82: Yes | N82: 6.56889 | O82: 3.37191 | P82: Legacy seed + Google Maps | Q82: 2026-09-16 | R82: 2026-09-16 | S82: Google-verified | T82: A - High commercial relevance | U82: Premium | V82: Not contacted | W82: Google/local result
A83: 82 | B83: IB Signature Salon | C83: Anthony / Anthony Village | D83: Anthony Village | E83: Salons | F83: Hair salon | G83: Anthony Village, 4 Olorunlogbon St, Maryland, Lagos, Nigeria | H83: +2348085873760 | J83: https://www.google.com/maps/place/?q=place_id:ChIJleRy64WNOxAR_Nu1JXzW10k | K83: 5 | L83: 1 | M83: Yes | N83: 6.5591189 | O83: 3.3703777 | P83: Google Maps (Apify scrape) | Q83: 2026-09-16 | R83: 2026-09-16 | S83: Google-verified | T83: B - Potential advertiser | U83: Standard | V83: Not Contacted
A84: 83 | B84: Inner Beauty Hair Shop | C84: Anthony / Anthony Village | D84: Anthony Village | E84: Salons | F84: Hair salon | G84: Anthony Village, 14 Olorunlogbon St | M84: No | N84: 6.55977 | O84: 3.37034 | P84: Google Maps (verified search) | Q84: 2026-09-16 | R84: 2026-09-16 | S84: Google-verified | T84: C - Listing only (no contact yet) | U84: Listing | V84: Not Contacted
A85: 84 | B85: Jeremynailss | C85: Anthony / Anthony Village | D85: 40 Oyedele Ogunniyi St | E85: Salons | F85: Nail salon | G85: 40 Oyedele Ogunniyi St | K85: 5 | L85: 2 | M85: No | N85: 6.56279 | O85: 3.371 | P85: Google Maps (verified search) | Q85: 2026-09-16 | R85: 2026-09-16 | S85: Google-verified | T85: C - Listing only (no contact yet) | U85: Listing | V85: Not Contacted
A86: 85 | B86: Lady B Hair Dressing Salon | C86: Anthony / Anthony Village | D86: 21 Olorunlogbon St | E86: Salons | F86: Hair salon | G86: 21 Olorunlogbon St, Anthony, Lagos 105102, Lagos, Nigeria | H86: +2348132594277 | J86: https://www.google.com/maps/place/?q=place_id:ChIJq1rY5ayNOxARGk0tK5kAzeY | M86: Yes | N86: 6.5603042 | O86: 3.3700472 | P86: Google Maps (Apify scrape) | Q86: 2026-09-16 | R86: 2026-09-16 | S86: Google-verified | T86: B - Potential advertiser | U86: Standard | V86: Not Contacted
A87: 86 | B87: Li-Labake Hair Salon | C87: Anthony / Anthony Village | D87: 17 Saji Ayangade St | E87: Salons | F87: Beauty salon | G87: 17 Saji Ayangade St | K87: 5 | L87: 1 | M87: No | N87: 6.56249 | O87: 3.37255 | P87: Google Maps (verified search) | Q87: 2026-09-16 | R87: 2026-09-16 | S87: Google-verified | T87: C - Listing only (no contact yet) | U87: Listing | V87: Not Contacted
A88: 87 | B88: M & M Beauty Palace | C88: Anthony / Anthony Village | D88: H95C+P4M | E88: Salons | F88: Beauty salon | G88: H95C+P4M, Anyony Village Road, Olorunlogbon St, Anthony Village, Lagos, Nigeria | J88: https://www.google.com/maps/place/?q=place_id:ChIJJYQTbzyNOxARlVMfyU1rzss | M88: No | N88: 6.5593394 | O88: 3.370309 | P88: Google Maps (Apify scrape) | Q88: 2026-09-16 | R88: 2026-09-16 | S88: Google-verified | T88: C - Listing only (no contact yet) | U88: Listing | V88: Not Contacted
A89: 88 | B89: Meg Braiding Centre | C89: Anthony / Anthony Village | D89: 9 Odofin Oyero Dr | E89: Salons | F89: Beauty salon | G89: 9 Odofin Oyero Dr, Kosofe, Lagos 105102, Lagos, Nigeria | H89: +2348088032077 | J89: https://www.google.com/maps/place/?q=place_id:ChIJT2lHFuuNOxARCZgd5m3Jrz0 | M89: Yes | N89: 6.560831 | O89: 3.3693642 | P89: Google Maps (Apify scrape) | Q89: 2026-09-16 | R89: 2026-09-16 | S89: Google-verified | T89: B - Potential advertiser | U89: Standard | V89: Not Contacted
A90: 89 | B90: Mohzaik Beauty Salon | C90: Anthony / Anthony Village | D90: 13 Sylvia Cres | E90: Salons | F90: Beauty salon | G90: 13 Sylvia Cres | K90: 5 | L90: 1 | M90: No | N90: 6.56213 | O90: 3.3677 | P90: Google Maps (verified search) | Q90: 2026-09-16 | R90: 2026-09-16 | S90: Google-verified | T90: C - Listing only (no contact yet) | U90: Listing | V90: Not Contacted
A91: 90 | B91: Nailz by Tm | C91: Anthony / Anthony Village | D91: 6 Oseni St | E91: Salons | F91: Nail salon | G91: 6 Oseni St, Anthony, Lagos 105102, Lagos, Nigeria | H91: +2348147659860 | I91: https://www.instagram.com/nailzbytm?igsh=MWUxbmVjbG54a204dA%3D%3D&utm_source=qr | J91: https://www.google.com/maps/place/?q=place_id:ChIJmwEEbACNOxARYE85iN2qfvw | K91: 5 | L91: 2 | M91: Yes | N91: 6.5578875 | O91: 3.3697909 | P91: Google Maps (Apify scrape) | Q91: 2026-09-16 | R91: 2026-09-16 | S91: Google-verified | T91: A - High commercial relevance | U91: Premium | V91: Not Contacted
A92: 91 | B92: Nene Hair Shop | C92: Anthony / Anthony Village | D92: 8 Oyedele Ogunniyi St | E92: Salons | F92: Beauty / Hair | G92: 8 Oyedele Ogunniyi St, Anthony, Lagos 100232 | H92: +2348026068658 | I92: business listing | M92: Yes | P92: Legacy seed (Finelib / NGEX / Cybo) | Q92: 2026-09-16 | R92: 2026-09-16 | S92: Directory listing only | T92: A - High commercial relevance | U92: Premium | V92: Not Contacted
A93: 92 | B93: Nobel Afrik | C93: Anthony / Anthony Village | D93: Wema Bank | E93: Salons | F93: Beauty salon | G93: Wema Bank, Mr Biggs, 2 Mobolaji Bank Anthony Way | K93: 5 | L93: 1 | M93: No | N93: 6.5718 | O93: 3.36641 | P93: Google Maps (verified search) | Q93: 2026-09-16 | R93: 2026-09-16 | S93: Google-verified | T93: C - Listing only (no contact yet) | U93: Listing | V93: Not Contacted
A94: 93 | B94: Purple Beautician (BEAUTY, HAIR & SPA) | C94: Anthony / Anthony Village | D94: 57B Faramobi Ajike St | E94: Salons | F94: Beauty / Salon | G94: 57B Faramobi Ajike St, Anthony, Lagos 100241 | H94: +2347017237271 | I94: https://purplebeautician.com/ | J94: https://www.google.com/maps/place/?q=place_id:ChIJVVGVjC6NOxARj2RldlFx-vE | K94: 5 | L94: 18 | M94: Yes | N94: 6.5599801 | O94: 3.3689518 | P94: Legacy seed + Google Maps | Q94: 2026-09-16 | R94: 2026-09-16 | S94: Google-verified | T94: A - High commercial relevance | U94: Premium | V94: Not Contacted
A95: 94 | B95: Queen Unisex Salon | C95: Anthony / Anthony Village | D95: 6 Odofin Oyero Dr | E95: Salons | F95: Hair care service | G95: 6 Odofin Oyero Dr, Anthony, Lagos 105102, Lagos, Nigeria | H95: +2348182158497 | J95: https://www.google.com/maps/place/?q=place_id:ChIJi0zkjoWNOxARceA4rchyYrU | K95: 4 | L95: 1 | M95: Yes | N95: 6.5599354 | O95: 3.369588 | P95: Google Maps (Apify scrape) | Q95: 2026-09-16 | R95: 2026-09-16 | S95: Google-verified | T95: B - Potential advertiser | U95: Standard | V95: Not Contacted
A96: 95 | B96: Rukky Beauty Salon | C96: Anthony / Anthony Village | D96: 1 Odofin Oyero Dr | E96: Salons | F96: Beauty salon | G96: 1 Odofin Oyero Dr, Anthony, Lagos 105102, Lagos, Nigeria | H96: +2348085108539 | J96: https://www.google.com/maps/place/?q=place_id:ChIJzbvhhoWNOxAR9tx0ZhoXVh4 | M96: Yes | N96: 6.5595916 | O96: 3.3692552 | P96: Google Maps (Apify scrape) | Q96: 2026-09-16 | R96: 2026-09-16 | S96: Google-verified | T96: B - Potential advertiser | U96: Standard | V96: Not Contacted
A97: 96 | B97: Sammy Z Unisex Salon | C97: Anthony / Anthony Village | D97: 16 Odofin Oyero Dr | E97: Salons | F97: Beauty salon | G97: 16 Odofin Oyero Dr, Anthony, Lagos 105102, Lagos, Nigeria | H97: +2347013114446 | J97: https://www.google.com/maps/place/?q=place_id:ChIJDQ-raAiNOxARrYBH7wSPdMI | M97: Yes | N97: 6.5607566 | O97: 3.3696575 | P97: Google Maps (Apify scrape) | Q97: 2026-09-16 | R97: 2026-09-16 | S97: Google-verified | T97: B - Potential advertiser | U97: Standard | V97: Not Contacted
A98: 97 | B98: Spanache Day Spa | C98: Anthony / Anthony Village | D98: 22 Odunlami Street | E98: Salons | F98: Beauty Salons and Spas | G98: 22 Odunlami Street, Anthony Village, Lagos | H98: +2348161824280 | M98: Yes | P98: Legacy seed (Finelib / NGEX / Cybo) | Q98: 2026-09-16 | R98: 2026-09-16 | S98: Directory listing only | T98: B - Potential advertiser | U98: Standard | V98: Not Contacted
A99: 98 | B99: Styledbykosii | C99: Anthony / Anthony Village | D99: 2 Odofin Oyero Dr | E99: Salons | F99: Hairdresser | G99: 2 Odofin Oyero Dr, Kosofe, Lagos 105102, Lagos, Nigeria | H99: +2347038271180 | J99: https://www.google.com/maps/place/?q=place_id:ChIJ93gTrCyNOxARpcjdjVZnFEA | M99: Yes | N99: 6.5595506 | O99: 3.3695672 | P99: Google Maps (Apify scrape) | Q99: 2026-09-16 | R99: 2026-09-16 | S99: Google-verified | T99: B - Potential advertiser | U99: Standard | V99: Not Contacted
A100: 99 | B100: Talking Faces | C100: Anthony / Anthony Village | D100: 1 Kunle Adebowale St | E100: Salons | F100: Beauty salon | G100: 1 Kunle Adebowale St | K100: 5 | L100: 2 | M100: No | N100: 6.56085 | O100: 3.37168 | P100: Google Maps (verified search) | Q100: 2026-09-16 | R100: 2026-09-16 | S100: Google-verified | T100: C - Listing only (no contact yet) | U100: Listing | V100: Not Contacted
...

Sheet AREA SUMMARY
A1: COVERAGE BY CATCHMENT
A3: Catchment | B3: Businesses | C3: % of database | D3: Priority A | E3: Priority B | F3: Priority C | G3: With phone | H3: Google-verified
A4: Anthony / Anthony Village | B4: =COUNTIF('MASTER DATABASE'!$C$2:$C$931,$A4) -> 478 | C4: =IFERROR(B4/$B$6,0) -> 0.51397849 | D4: =COUNTIFS('MASTER DATABASE'!$C$2:$C$931,$A4,'MASTER DATABASE'!$T$2:$T$931,"A - High commercial relevance") -> 107 | E4: =COUNTIFS('MASTER DATABASE'!$C$2:$C$931,$A4,'MASTER DATABASE'!$T$2:$T$931,"B - Potential advertiser") -> 246 | F4: =COUNTIFS('MASTER DATABASE'!$C$2:$C$931,$A4,'MASTER DATABASE'!$T$2:$T$931,"C - Listing only (no contact yet)") -> 125 | G4: =COUNTIFS('MASTER DATABASE'!$C$2:$C$931,$A4,'MASTER DATABASE'!$M$2:$M$931,"Yes") -> 353 | H4: =COUNTIFS('MASTER DATABASE'!$C$2:$C$931,$A4,'MASTER DATABASE'!$S$2:$S$931,"Google-verified") -> 331
A5: Maryland / Mende | B5: =COUNTIF('MASTER DATABASE'!$C$2:$C$931,$A5) -> 452 | C5: =IFERROR(B5/$B$6,0) -> 0.48602151 | D5: =COUNTIFS('MASTER DATABASE'!$C$2:$C$931,$A5,'MASTER DATABASE'!$T$2:$T$931,"A - High commercial relevance") -> 45 | E5: =COUNTIFS('MASTER DATABASE'!$C$2:$C$931,$A5,'MASTER DATABASE'!$T$2:$T$931,"B - Potential advertiser") -> 161 | F5: =COUNTIFS('MASTER DATABASE'!$C$2:$C$931,$A5,'MASTER DATABASE'!$T$2:$T$931,"C - Listing only (no contact yet)") -> 246 | G5: =COUNTIFS('MASTER DATABASE'!$C$2:$C$931,$A5,'MASTER DATABASE'!$M$2:$M$931,"Yes") -> 206 | H5: =COUNTIFS('MASTER DATABASE'!$C$2:$C$931,$A5,'MASTER DATABASE'!$S$2:$S$931,"Google-verified") -> 393
A6: TOTAL | B6: =SUM(B4:B5) -> 930 | C6: =IFERROR(B6/$B$6,0) -> 1 | D6: =SUM(D4:D5) -> 152 | E6: =SUM(E4:E5) -> 407 | F6: =SUM(F4:F5) -> 371 | G6: =SUM(G4:G5) -> 559 | H6: =SUM(H4:H5) -> 724

Sheet CATEGORY SUMMARY
A1: COVERAGE BY CATEGORY (18-CATEGORY TAXONOMY)
A3: Category | B3: Anthony / Anthony Village | C3: Maryland / Mende | D3: Total | E3: With phone | F3: Priority A | G3: Avg Google rating | H3: % of database
A4: Restaurants | B4: =COUNTIFS('MASTER DATABASE'!$C$2:$C$931,$B$3,'MASTER DATABASE'!$E$2:$E$931,$A4) -> 34 | C4: =COUNTIFS('MASTER DATABASE'!$C$2:$C$931,$C$3,'MASTER DATABASE'!$E$2:$E$931,$A4) -> 63 | D4: =SUM(B4:C4) -> 97 | E4: =COUNTIFS('MASTER DATABASE'!$E$2:$E$931,$A4,'MASTER DATABASE'!$M$2:$M$931,"Yes") -> 26 | F4: =COUNTIFS('MASTER DATABASE'!$E$2:$E$931,$A4,'MASTER DATABASE'!$T$2:$T$931,"A - High commercial relevance") -> 7 | G4: =IFERROR(AVERAGEIFS('MASTER DATABASE'!$K$2:$K$931,'MASTER DATABASE'!$E$2:$E$931,$A4,'MASTER DATABASE'!$K$2:$K$931,">0"),"n/a") -> 4.0885246 | H4: =IFERROR(D4/$D$22,0) -> 0.10430108
A5: Hotels | B5: =COUNTIFS('MASTER DATABASE'!$C$2:$C$931,$B$3,'MASTER DATABASE'!$E$2:$E$931,$A5) -> 11 | C5: =COUNTIFS('MASTER DATABASE'!$C$2:$C$931,$C$3,'MASTER DATABASE'!$E$2:$E$931,$A5) -> 14 | D5: =SUM(B5:C5) -> 25 | E5: =COUNTIFS('MASTER DATABASE'!$E$2:$E$931,$A5,'MASTER DATABASE'!$M$2:$M$931,"Yes") -> 10 | F5: =COUNTIFS('MASTER DATABASE'!$E$2:$E$931,$A5,'MASTER DATABASE'!$T$2:$T$931,"A - High commercial relevance") -> 4 | G5: =IFERROR(AVERAGEIFS('MASTER DATABASE'!$K$2:$K$931,'MASTER DATABASE'!$E$2:$E$931,$A5,'MASTER DATABASE'!$K$2:$K$931,">0"),"n/a") -> 3.8944444 | H5: =IFERROR(D5/$D$22,0) -> 0.02688172
A6: Gyms | B6: =COUNTIFS('MASTER DATABASE'!$C$2:$C$931,$B$3,'MASTER DATABASE'!$E$2:$E$931,$A6) -> 15 | C6: =COUNTIFS('MASTER DATABASE'!$C$2:$C$931,$C$3,'MASTER DATABASE'!$E$2:$E$931,$A6) -> 12 | D6: =SUM(B6:C6) -> 27 | E6: =COUNTIFS('MASTER DATABASE'!$E$2:$E$931,$A6,'MASTER DATABASE'!$M$2:$M$931,"Yes") -> 11 | F6: =COUNTIFS('MASTER DATABASE'!$E$2:$E$931,$A6,'MASTER DATABASE'!$T$2:$T$931,"A - High commercial relevance") -> 1 | G6: =IFERROR(AVERAGEIFS('MASTER DATABASE'!$K$2:$K$931,'MASTER DATABASE'!$E$2:$E$931,$A6,'MASTER DATABASE'!$K$2:$K$931,">0"),"n/a") -> 4.5294118 | H6: =IFERROR(D6/$D$22,0) -> 0.029032258
A7: Salons | B7: =COUNTIFS('MASTER DATABASE'!$C$2:$C$931,$B$3,'MASTER DATABASE'!$E$2:$E$931,$A7) -> 43 | C7: =COUNTIFS('MASTER DATABASE'!$C$2:$C$931,$C$3,'MASTER DATABASE'!$E$2:$E$931,$A7) -> 79 | D7: =SUM(B7:C7) -> 122 | E7: =COUNTIFS('MASTER DATABASE'!$E$2:$E$931,$A7,'MASTER DATABASE'!$M$2:$M$931,"Yes") -> 33 | F7: =COUNTIFS('MASTER DATABASE'!$E$2:$E$931,$A7,'MASTER DATABASE'!$T$2:$T$931,"A - High commercial relevance") -> 11 | G7: =IFERROR(AVERAGEIFS('MASTER DATABASE'!$K$2:$K$931,'MASTER DATABASE'!$E$2:$E$931,$A7,'MASTER DATABASE'!$K$2:$K$931,">0"),"n/a") -> 4.5436364 | H7: =IFERROR(D7/$D$22,0) -> 0.1311828
A8: Barbers | B8: =COUNTIFS('MASTER DATABASE'!$C$2:$C$931,$B$3,'MASTER DATABASE'!$E$2:$E$931,$A8) -> 8 | C8: =COUNTIFS('MASTER DATABASE'!$C$2:$C$931,$C$3,'MASTER DATABASE'!$E$2:$E$931,$A8) -> 10 | D8: =SUM(B8:C8) -> 18 | E8: =COUNTIFS('MASTER DATABASE'!$E$2:$E$931,$A8,'MASTER DATABASE'!$M$2:$M$931,"Yes") -> 5 | F8: =COUNTIFS('MASTER DATABASE'!$E$2:$E$931,$A8,'MASTER DATABASE'!$T$2:$T$931,"A - High commercial relevance") -> 1 | G8: =IFERROR(AVERAGEIFS('MASTER DATABASE'!$K$2:$K$931,'MASTER DATABASE'!$E$2:$E$931,$A8,'MASTER DATABASE'!$K$2:$K$931,">0"),"n/a") -> 4.4333333 | H8: =IFERROR(D8/$D$22,0) -> 0.019354839
A9: Medical Centres | B9: =COUNTIFS('MASTER DATABASE'!$C$2:$C$931,$B$3,'MASTER DATABASE'!$E$2:$E$931,$A9) -> 31 | C9: =COUNTIFS('MASTER DATABASE'!$C$2:$C$931,$C$3,'MASTER DATABASE'!$E$2:$E$931,$A9) -> 29 | D9: =SUM(B9:C9) -> 60 | E9: =COUNTIFS('MASTER DATABASE'!$E$2:$E$931,$A9,'MASTER DATABASE'!$M$2:$M$931,"Yes") -> 49 | F9: =COUNTIFS('MASTER DATABASE'!$E$2:$E$931,$A9,'MASTER DATABASE'!$T$2:$T$931,"A - High commercial relevance") -> 18 | G9: =IFERROR(AVERAGEIFS('MASTER DATABASE'!$K$2:$K$931,'MASTER DATABASE'!$E$2:$E$931,$A9,'MASTER DATABASE'!$K$2:$K$931,">0"),"n/a") -> 4.2709677 | H9: =IFERROR(D9/$D$22,0) -> 0.064516129
A10: Dentists | B10: =COUNTIFS('MASTER DATABASE'!$C$2:$C$931,$B$3,'MASTER DATABASE'!$E$2:$E$931,$A10) -> 6 | C10: =COUNTIFS('MASTER DATABASE'!$C$2:$C$931,$C$3,'MASTER DATABASE'!$E$2:$E$931,$A10) -> 3 | D10: =SUM(B10:C10) -> 9 | E10: =COUNTIFS('MASTER DATABASE'!$E$2:$E$931,$A10,'MASTER DATABASE'!$M$2:$M$931,"Yes") -> 9 | F10: =COUNTIFS('MASTER DATABASE'!$E$2:$E$931,$A10,'MASTER DATABASE'!$T$2:$T$931,"A - High commercial relevance") -> 3 | G10: =IFERROR(AVERAGEIFS('MASTER DATABASE'!$K$2:$K$931,'MASTER DATABASE'!$E$2:$E$931,$A10,'MASTER DATABASE'!$K$2:$K$931,">0"),"n/a") -> 4.75 | H10: =IFERROR(D10/$D$22,0) -> 0.0096774194
A11: Pharmacies | B11: =COUNTIFS('MASTER DATABASE'!$C$2:$C$931,$B$3,'MASTER DATABASE'!$E$2:$E$931,$A11) -> 13 | C11: =COUNTIFS('MASTER DATABASE'!$C$2:$C$931,$C$3,'MASTER DATABASE'!$E$2:$E$931,$A11) -> 24 | D11: =SUM(B11:C11) -> 37 | E11: =COUNTIFS('MASTER DATABASE'!$E$2:$E$931,$A11,'MASTER DATABASE'!$M$2:$M$931,"Yes") -> 31 | F11: =COUNTIFS('MASTER DATABASE'!$E$2:$E$931,$A11,'MASTER DATABASE'!$T$2:$T$931,"A - High commercial relevance") -> 5 | G11: =IFERROR(AVERAGEIFS('MASTER DATABASE'!$K$2:$K$931,'MASTER DATABASE'!$E$2:$E$931,$A11,'MASTER DATABASE'!$K$2:$K$931,">0"),"n/a") -> 4.224 | H11: =IFERROR(D11/$D$22,0) -> 0.039784946
A12: Schools | B12: =COUNTIFS('MASTER DATABASE'!$C$2:$C$931,$B$3,'MASTER DATABASE'!$E$2:$E$931,$A12) -> 12 | C12: =COUNTIFS('MASTER DATABASE'!$C$2:$C$931,$C$3,'MASTER DATABASE'!$E$2:$E$931,$A12) -> 21 | D12: =SUM(B12:C12) -> 33 | E12: =COUNTIFS('MASTER DATABASE'!$E$2:$E$931,$A12,'MASTER DATABASE'!$M$2:$M$931,"Yes") -> 14 | F12: =COUNTIFS('MASTER DATABASE'!$E$2:$E$931,$A12,'MASTER DATABASE'!$T$2:$T$931,"A - High commercial relevance") -> 1 | G12: =IFERROR(AVERAGEIFS('MASTER DATABASE'!$K$2:$K$931,'MASTER DATABASE'!$E$2:$E$931,$A12,'MASTER DATABASE'!$K$2:$K$931,">0"),"n/a") -> 4.5142857 | H12: =IFERROR(D12/$D$22,0) -> 0.035483871
A13: Churches | B13: =COUNTIFS('MASTER DATABASE'!$C$2:$C$931,$B$3,'MASTER DATABASE'!$E$2:$E$931,$A13) -> 11 | C13: =COUNTIFS('MASTER DATABASE'!$C$2:$C$931,$C$3,'MASTER DATABASE'!$E$2:$E$931,$A13) -> 14 | D13: =SUM(B13:C13) -> 25 | E13: =COUNTIFS('MASTER DATABASE'!$E$2:$E$931,$A13,'MASTER DATABASE'!$M$2:$M$931,"Yes") -> 4 | F13: =COUNTIFS('MASTER DATABASE'!$E$2:$E$931,$A13,'MASTER DATABASE'!$T$2:$T$931,"A - High commercial relevance") -> 3 | G13: =IFERROR(AVERAGEIFS('MASTER DATABASE'!$K$2:$K$931,'MASTER DATABASE'!$E$2:$E$931,$A13,'MASTER DATABASE'!$K$2:$K$931,">0"),"n/a") -> 4.7272727 | H13: =IFERROR(D13/$D$22,0) -> 0.02688172
A14: Supermarkets | B14: =COUNTIFS('MASTER DATABASE'!$C$2:$C$931,$B$3,'MASTER DATABASE'!$E$2:$E$931,$A14) -> 56 | C14: =COUNTIFS('MASTER DATABASE'!$C$2:$C$931,$C$3,'MASTER DATABASE'!$E$2:$E$931,$A14) -> 19 | D14: =SUM(B14:C14) -> 75 | E14: =COUNTIFS('MASTER DATABASE'!$E$2:$E$931,$A14,'MASTER DATABASE'!$M$2:$M$931,"Yes") -> 48 | F14: =COUNTIFS('MASTER DATABASE'!$E$2:$E$931,$A14,'MASTER DATABASE'!$T$2:$T$931,"A - High commercial relevance") -> 13 | G14: =IFERROR(AVERAGEIFS('MASTER DATABASE'!$K$2:$K$931,'MASTER DATABASE'!$E$2:$E$931,$A14,'MASTER DATABASE'!$K$2:$K$931,">0"),"n/a") -> 4.2093023 | H14: =IFERROR(D14/$D$22,0) -> 0.080645161
A15: Boutiques | B15: =COUNTIFS('MASTER DATABASE'!$C$2:$C$931,$B$3,'MASTER DATABASE'!$E$2:$E$931,$A15) -> 43 | C15: =COUNTIFS('MASTER DATABASE'!$C$2:$C$931,$C$3,'MASTER DATABASE'!$E$2:$E$931,$A15) -> 12 | D15: =SUM(B15:C15) -> 55 | E15: =COUNTIFS('MASTER DATABASE'!$E$2:$E$931,$A15,'MASTER DATABASE'!$M$2:$M$931,"Yes") -> 39 | F15: =COUNTIFS('MASTER DATABASE'!$E$2:$E$931,$A15,'MASTER DATABASE'!$T$2:$T$931,"A - High commercial relevance") -> 13 | G15: =IFERROR(AVERAGEIFS('MASTER DATABASE'!$K$2:$K$931,'MASTER DATABASE'!$E$2:$E$931,$A15,'MASTER DATABASE'!$K$2:$K$931,">0"),"n/a") -> 4.0166667 | H15: =IFERROR(D15/$D$22,0) -> 0.059139785
... A21: Caterers | B21: =COUNTIFS('MASTER DATABASE'!$C$2:$C$931,$B$3,'MASTER DATABASE'!$E$2:$E$931,$A21) -> 3 | C21: =COUNTIFS('MASTER DATABASE'!$C$2:$C$931,$C$3,'MASTER DATABASE'!$E$2:$E$931,$A21) -> 15 | D21: =SUM(B21:C21) -> 18 | E21: =COUNTIFS('MASTER DATABASE'!$E$2:$E$931,$A21,'MASTER DATABASE'!$M$2:$M$931,"Yes") -> 16 | F21: =COUNTIFS('MASTER DATABASE'!$E$2:$E$931,$A21,'MASTER DATABASE'!$T$2:$T$931,"A - High commercial relevance") -> 3 | G21: =IFERROR(AVERAGEIFS('MASTER DATABASE'!$K$2:$K$931,'MASTER DATABASE'!$E$2:$E$931,$A21,'MASTER DATABASE'!$K$2:$K$931,">0"),"n/a") -> 4.45 | H21: =IFERROR(D21/$D$22,0) -> 0.019354839
A22: TOTAL | B22: =SUM(B4:B21) -> 478 | C22: =SUM(C4:C21) -> 452 | D22: =SUM(D4:D21) -> 930 | E22: =SUM(E4:E21) -> 559 | F22: =SUM(F4:F21) -> 152 | H22: =IFERROR(D22/$D$22,0) -> 1

Sheet RESEARCH MATRIX
A1: RESEARCH MATRIX - WHERE THE GAPS ARE
A2: Target per cell is a planning benchmark for a catchment of this size, not a hard quota. Sort by Gap to see what to canvass next.
A4: Catchment | B4: Category | C4: Found | D4: Target | E4: Gap | F4: Coverage | G4: Status | H4: Next Action
A5: Anthony / Anthony Village | B5: Restaurants | C5: =COUNTIFS('MASTER DATABASE'!$C$2:$C$931,$A5,'MASTER DATABASE'!$E$2:$E$931,$B5) -> 34 | D5: 45 | E5: =MAX(0,D5-C5) -> 11 | F5: =IFERROR(MIN(1,C5/D5),0) -> 0.75555556 | G5: =IF(C5>=D5,"Target met",IF(C5>=D5*0.6,"Good coverage",IF(C5>0,"Thin - needs canvassing","Not yet searched"))) -> Good coverage | H5: =IF(C5>=D5,"Maintain - re-check quarterly","Street canvass "&$A5&" for "&$B5&", then verify on Google") -> Street canvass Anthony / Anthony Village for Restaurants, then verify on Google
A6: Anthony / Anthony Village | B6: Hotels | C6: =COUNTIFS('MASTER DATABASE'!$C$2:$C$931,$A6,'MASTER DATABASE'!$E$2:$E$931,$B6) -> 11 | D6: 15 | E6: =MAX(0,D6-C6) -> 4 | F6: =IFERROR(MIN(1,C6/D6),0) -> 0.73333333 | G6: =IF(C6>=D6,"Target met",IF(C6>=D6*0.6,"Good coverage",IF(C6>0,"Thin - needs canvassing","Not yet searched"))) -> Good coverage | H6: =IF(C6>=D6,"Maintain - re-check quarterly","Street canvass "&$A6&" for "&$B6&", then verify on Google") -> Street canvass Anthony / Anthony Village for Hotels, then verify on Google
A7: Anthony / Anthony Village | B7: Gyms | C7: =COUNTIFS('MASTER DATABASE'!$C$2:$C$931,$A7,'MASTER DATABASE'!$E$2:$E$931,$B7) -> 15 | D7: 12 | E7: =MAX(0,D7-C7) -> 0 | F7: =IFERROR(MIN(1,C7/D7),0) -> 1 | G7: =IF(C7>=D7,"Target met",IF(C7>=D7*0.6,"Good coverage",IF(C7>0,"Thin - needs canvassing","Not yet searched"))) -> Target met | H7: =IF(C7>=D7,"Maintain - re-check quarterly","Street canvass "&$A7&" for "&$B7&", then verify on Google") -> Maintain - re-check quarterly
A8: Anthony / Anthony Village | B8: Salons | C8: =COUNTIFS('MASTER DATABASE'!$C$2:$C$931,$A8,'MASTER DATABASE'!$E$2:$E$931,$B8) -> 43 | D8: 60 | E8: =MAX(0,D8-C8) -> 17 | F8: =IFERROR(MIN(1,C8/D8),0) -> 0.71666667 | G8: =IF(C8>=D8,"Target met",IF(C8>=D8*0.6,"Good coverage",IF(C8>0,"Thin - needs canvassing","Not yet searched"))) -> Good coverage | H8: =IF(C8>=D8,"Maintain - re-check quarterly","Street canvass "&$A8&" for "&$B8&", then verify on Google") -> Street canvass Anthony / Anthony Village for Salons, then verify on Google
A9: Anthony / Anthony Village | B9: Barbers | C9: =COUNTIFS('MASTER DATABASE'!$C$2:$C$931,$A9,'MASTER DATABASE'!$E$2:$E$931,$B9) -> 8 | D9: 25 | E9: =MAX(0,D9-C9) -> 17 | F9: =IFERROR(MIN(1,C9/D9),0) -> 0.32 | G9: =IF(C9>=D9,"Target met",IF(C9>=D9*0.6,"Good coverage",IF(C9>0,"Thin - needs canvassing","Not yet searched"))) -> Thin - needs canvassing | H9: =IF(C9>=D9,"Maintain - re-check quarterly","Street canvass "&$A9&" for "&$B9&", then verify on Google") -> Street canvass Anthony / Anthony Village for Barbers, then verify on Google
A10: Anthony / Anthony Village | B10: Medical Centres | C10: =COUNTIFS('MASTER DATABASE'!$C$2:$C$931,$A10,'MASTER DATABASE'!$E$2:$E$931,$B10) -> 31 | D10: 30 | E10: =MAX(0,D10-C10) -> 0 | F10: =IFERROR(MIN(1,C10/D10),0) -> 1 | G10: =IF(C10>=D10,"Target met",IF(C10>=D10*0.6,"Good coverage",IF(C10>0,"Thin - needs canvassing","Not yet searched"))) -> Target met | H10: =IF(C10>=D10,"Maintain - re-check quarterly","Street canvass "&$A10&" for "&$B10&", then verify on Google") -> Maintain - re-check quarterly
A11: Anthony / Anthony Village | B11: Dentists | C11: =COUNTIFS('MASTER DATABASE'!$C$2:$C$931,$A11,'MASTER DATABASE'!$E$2:$E$931,$B11) -> 6 | D11: 8 | E11: =MAX(0,D11-C11) -> 2 | F11: =IFERROR(MIN(1,C11/D11),0) -> 0.75 | G11: =IF(C11>=D11,"Target met",IF(C11>=D11*0.6,"Good coverage",IF(C11>0,"Thin - needs canvassing","Not yet searched"))) -> Good coverage | H11: =IF(C11>=D11,"Maintain - re-check quarterly","Street canvass "&$A11&" for "&$B11&", then verify on Google") -> Street canvass Anthony / Anthony Village for Dentists, then verify on Google
A12: Anthony / Anthony Village | B12: Pharmacies | C12: =COUNTIFS('MASTER DATABASE'!$C$2:$C$931,$A12,'MASTER DATABASE'!$E$2:$E$931,$B12) -> 13 | D12: 22 | E12: =MAX(0,D12-C12) -> 9 | F12: =IFERROR(MIN(1,C12/D12),0) -> 0.59090909 | G12: =IF(C12>=D12,"Target met",IF(C12>=D12*0.6,"Good coverage",IF(C12>0,"Thin - needs canvassing","Not yet searched"))) -> Thin - needs canvassing | H12: =IF(C12>=D12,"Maintain - re-check quarterly","Street canvass "&$A12&" for "&$B12&", then verify on Google") -> Street canvass Anthony / Anthony Village for Pharmacies, then verify on Google
A13: Anthony / Anthony Village | B13: Schools | C13: =COUNTIFS('MASTER DATABASE'!$C$2:$C$931,$A13,'MASTER DATABASE'!$E$2:$E$931,$B13) -> 12 | D13: 30 | E13: =MAX(0,D13-C13) -> 18 | F13: =IFERROR(MIN(1,C13/D13),0) -> 0.4 | G13: =IF(C13>=D13,"Target met",IF(C13>=D13*0.6,"Good coverage",IF(C13>0,"Thin - needs canvassing","Not yet searched"))) -> Thin - needs canvassing | H13: =IF(C13>=D13,"Maintain - re-check quarterly","Street canvass "&$A13&" for "&$B13&", then verify on Google") -> Street canvass Anthony / Anthony Village for Schools, then verify on Google
A14: Anthony / Anthony Village | B14: Churches | C14: =COUNTIFS('MASTER DATABASE'!$C$2:$C$931,$A14,'MASTER DATABASE'!$E$2:$E$931,$B14) -> 11 | D14: 25 | E14: =MAX(0,D14-C14) -> 14 | F14: =IFERROR(MIN(1,C14/D14),0) -> 0.44 | G14: =IF(C14>=D14,"Target met",IF(C14>=D14*0.6,"Good coverage",IF(C14>0,"Thin - needs canvassing","Not yet searched"))) -> Thin - needs canvassing | H14: =IF(C14>=D14,"Maintain - re-check quarterly","Street canvass "&$A14&" for "&$B14&", then verify on Google") -> Street canvass Anthony / Anthony Village for Churches, then verify on Google
A15: Anthony / Anthony Village | B15: Supermarkets | C15: =COUNTIFS('MASTER DATABASE'!$C$2:$C$931,$A15,'MASTER DATABASE'!$E$2:$E$931,$B15) -> 56 | D15: 35 | E15: =MAX(0,D15-C15) -> 0 | F15: =IFERROR(MIN(1,C15/D15),0) -> 1 | G15: =IF(C15>=D15,"Target met",IF(C15>=D15*0.6,"Good coverage",IF(C15>0,"Thin - needs canvassing","Not yet searched"))) -> Target met | H15: =IF(C15>=D15,"Maintain - re-check quarterly","Street canvass "&$A15&" for "&$B15&", then verify on Google") -> Maintain - re-check quarterly
A16: Anthony / Anthony Village | B16: Boutiques | C16: =COUNTIFS('MASTER DATABASE'!$C$2:$C$931,$A16,'MASTER DATABASE'!$E$2:$E$931,$B16) -> 43 | D16: 40 | E16: =MAX(0,D16-C16) -> 0 | F16: =IFERROR(MIN(1,C16/D16),0) -> 1 | G16: =IF(C16>=D16,"Target met",IF(C16>=D16*0.6,"Good coverage",IF(C16>0,"Thin - needs canvassing","Not yet searched"))) -> Target met | H16: =IF(C16>=D16,"Maintain - re-check quarterly","Street canvass "&$A16&" for "&$B16&", then verify on Google") -> Maintain - re-check quarterly
... A40: Maryland / Mende | B40: Caterers | C40: =COUNTIFS('MASTER DATABASE'!$C$2:$C$931,$A40,'MASTER DATABASE'!$E$2:$E$931,$B40) -> 15 | D40: 15 | E40: =MAX(0,D40-C40) -> 0 | F40: =IFERROR(MIN(1,C40/D40),0) -> 1 | G40: =IF(C40>=D40,"Target met",IF(C40>=D40*0.6,"Good coverage",IF(C40>0,"Thin - needs canvassing","Not yet searched"))) -> Target met | H40: =IF(C40>=D40,"Maintain - re-check quarterly","Street canvass "&$A40&" for "&$B40&", then verify on Google") -> Maintain - re-check quarterly

Sheet SOURCE LOG
A1: WHERE THE DATA CAME FROM
A3: Source | B3: What it contributed | C3: Records | D3: How it was used | E3: Reference
A4: Google Maps (Apify scrape) | B4: Names, addresses, phones, websites, ratings, review counts and coordinates for the Anthony Village catchment across 48 category searches. | C4: 242 | D4: Primary discovery + verification for Anthony | E4: https://apify.com/compass/crawler-google-places
A5: Google Maps (verified search) | B5: The same fields for the Maryland / Mende catchment, collected across 28 category searches centred on 6.5700 / 3.3685. | C5: 431 | D5: Primary discovery + verification for Maryland | E5: https://www.google.com/maps
A6: Legacy seed database | B6: The 265 records in the previous workbook, sourced from Finelib, NGEX, Cybo and local search. | C6: 206 | D6: Retained in full; re-categorised and re-assigned by catchment | E6: Anthony_Community_Media_MASTER_DATABASE_SUMMARIES_POPULATED.xlsx
A7: Legacy + Google (merged) | B7: Records that appeared in both the old database and Google Maps, merged into a single richer row. | C7: 51 | D7: Cross-verification - highest confidence records | E7: Both of the above
A8: Finelib | B8: Area and category business listings with phones and addresses. | C8: see legacy | D8: Directory cross-reference | E8: https://www.finelib.com/cities/lagos/areas-and-suburbs/anthony-village
A9: NGEX | B9: Area and category listings and business profiles. | C9: see legacy | D9: Cross-reference + categories | E9: https://ngex.com/
A10: Cybo | B10: Street and postal-code business listings. | C10: see legacy | D10: Cross-reference | E10: https://www.cybo.com/
A11: OpenStreetMap | B11: Street-level points of interest used to confirm the true boundaries of the Maryland / Mende catchment. | C11: boundary check | D11: Geographic validation only | E11: https://www.openstreetmap.org/

Sheet OUT-OF-AREA POOL
A1: OUT-OF-AREA POOL (NOT PART OF THE MASTER COUNT)
A2: Businesses captured by the same scrape that fall outside the two target catchments - mostly Ilupeju, Gbagada, Obanikoro, Oshodi and Ikeja GRA. Kept here in case the magazine expands its footprint. These are NOT counted anywhere else in this workbook.
A4: Business Name | B4: Category | C4: Source Category | D4: Full Address | E4: Phone | F4: Website | G4: Google Rating | H4: Google Reviews
A5: 157 GARDENS EVENT CENTER | B5: Event Businesses | C5: Event venue | D5: 157 Ikorodu Rd, Onipanu, Lagos 102215, Lagos, Nigeria | E5: +2349033984069 | F5: https://www.157gardens.com/ | G5: 4.3 | H5: 36
A6: 2talk Barbershop | B6: Barbers | C6: Barber shop | D6: 2 idera street oworonshoki, 2 Idera St, Oworosoki, Lagos, Nigeria | E6: +2348082868332 | F6: https://2talk-barbershop.vercel.app/ | G6: 4 | H6: 1
A7: 34SND Pictures | B7: Event Businesses | C7: Photography studio | D7: 1 Buraimoh St, Obanikoro, Lagos 102216, Lagos, Nigeria | E7: +2347010335542 | G7: 4.8 | H7: 39
A8: 369 Concepts | B8: Boutiques | C8: Computer repair service | D8: 23 Obalodu St, Ilupeju, Lagos 102215, Lagos, Nigeria | E8: +2348127202139
A9: A New U Gym and Spa | B9: Gyms | C9: Gym | D9: 52 Salaudeen Akano St, Kosofe, Lagos 105102, Lagos, Nigeria | E9: +2348033083244 | G9: 4 | H9: 25
A10: A1 PLUMBING SOLUTIONS | B10: Home Services | C10: Plumber | D10: H86W+9V3, Akinpelu St, Mafoluku Oshodi, Lagos 102214, Lagos, Nigeria | E10: +2347060718725 | G10: 5 | H10: 1
A11: A2 Barber Shop | B11: Barbers | C11: Barber shop | D11: 27 Adifase St, Somolu, Lagos 102216, Lagos, Nigeria | G11: 5 | H11: 1
A12: AA Store | B12: Supermarkets | C12: Supermarket | D12: Lagos NG, 4 Alaba St, Oworosoki, Oworonshoki 105102, Lagos, Nigeria | E12: +2348025619340
A13: AB Electronics | B13: Home Services | C13: Electrician | D13: Oshodi Road Oshodi Local Government Area, Oshodi-Isolo, Lagos, Nigeria | E13: +2348130409105 | G13: 5 | H13: 1
A14: AB Soyemi Car Wash | B14: Auto Services | C14: Car wash | D14: 32 Boladale St, Orile Oshodi, Lagos 102214, Lagos, Nigeria | G14: 5 | H14: 1
A15: Abbey Japanese Mechanical Specialist | B15: Auto Services | C15: Auto repair shop | D15: Akinyemi Street off Fatai Atare, Matori Street, Way, Lagos, Nigeria | E15: +2348186586747
A16: Abdul Lateef Memorial School | B16: Schools | C16: Primary school | D16: Local Government, 14 Pako Bustop, Apapa Oworonshoki Expy, Kosofe, Oworonshoki 100221, Lagos, Nigeria | E16: +2348179181712
A17: Abednigo Nursery school | B17: Schools | C17: Kindergarten | D17: 12 C.A.C St, Papa Ajao, Lagos 102215, Lagos, Nigeria
A18: Abitex trading Store(main store) | B18: Supermarkets | C18: Clothing store | D18: Oshodi market, 8, Macarthy lane, off Brown St, Oshodi, Lagos, Nigeria | E18: +2348037195943 | G18: 4 | H18: 1
A19: Abiye Clinic and Maternity Home | B19: Medical Centres | C19: Medical clinic | D19: HC42+299, Oworosoki, Lagos 105102, Lagos, Nigeria
A20: Academy Press PLC | B20: Professional Services | C20: Commercial printer | D20: 28/32 Ilupeju Industrial Ave, Ilupeju, Lagos 100252, Lagos, Nigeria | E20: +2349030001367 | F20: http://academypress-plc.com/ | G20: 4.3 | H20: 55
A21: Acculab Diagnostic Limited | B21: Medical Centres | C21: Diagnostic center | D21: 62 Jagun Molu St, Bariga, Lagos 100223, Lagos, Nigeria | E21: +2347050948565 | G21: 4.5 | H21: 2
A22: Acem Insurance | B22: Professional Services | C22: Insurance agency | D22: H948+3RG, Ikorodu Road Service Lane, Ilupeju, Lagos 102216, Lagos, Nigeria | G22: 4 | H22: 1
A23: Acharomi plumbing solution | B23: Home Services | C23: Plumber | D23: 9 Akin-Lawanson St, Oshodi-Isolo, Lagos 102214, Lagos, Nigeria | E23: +2349035870924
A24: Acorn Insurance Brokers Ltd | B24: Professional Services | C24: Insurance agency | D24: 223 Ikorodu Rd, Ilupeju, Lagos 100252, Lagos, Nigeria | G24: 5 | H24: 1
A25: ADAspecial catering services | B25: Auto Services | C25: Parking garage | D25: 25 Adeyinka St, Ilupeju, Lagos 102215, Lagos, Nigeria | E25: +2348066460771
A26: Addide Akoka Supermarket | B26: Supermarkets | C26: Supermarket | D26: 75 St Finbarr's College Rd, Akoka, Lagos 102216, Lagos, Nigeria | E26: +2348024335018 | F26: http://www.addide.com/ | G26: 3.8 | H26: 338
A27: Addide HQ | B27: Supermarkets | C27: Supermarket | D27: 16/18 Dahomey St, Somolu, Barriga 102216, Lagos, Nigeria | F27: http://www.addide.com/ | G27: 4.1 | H27: 595
A28: Adebiyi Eniola Photography | B28: Event Businesses | C28: Photographer | D28: 6 Oluseun Cres, behind corona school, Gbagada, Lagos 200001, Lagos, Nigeria | E28: +2347081804286
A29: Adedoyin spa | B29: Salons | C29: Spa | D29: 4 BODE JOSEPH STR, Oworo Rd, Yaba, Lagos, Nigeria | E29: +2348035781634
A30: Adegbite Adeyemo & Co (Chartered Accountants) | B30: Professional Services | C30: Accounting firm | D30: 23 Obalodu St, Ilupeju, Lagos 102215, Lagos, Nigeria | E30: +2348029112556 | F30: http://www.adegbiteadeyemo.com/ | G30: 3.5 | H30: 2
A31: Ademola Dere & Co | B31: Professional Services | C31: Legal services | D31: Odi-olowo, 6 Coker Rd, Ilupeju, Lagos 102215, Lagos, Nigeria | E31: +2348039118528
A32: Adewale Plumbing Ltd | B32: Home Services | C32: Plumber | D32: Old Adeoye St, Mafoluku Oshodi, Lagos 102214, Lagos, Nigeria
A33: Adex Beauty Salon | B33: Salons | C33: Hair salon | D33: 7 Adetoke St, Brigade, Lagos 102216, Lagos, Nigeria | E33: +2348081633847
A34: Adexen | B34: Auto Services | C34: Parking garage | D34: Allied House, 227 Town Planning Way, Ikorodu Rd, Ilupeju, Lagos 102215, Lagos, Nigeria | E34: +2348024346820 | F34: http://www.adexen.com/ | G34: 4 | H34: 2
A35: Adeyemi Provision Store | B35: Supermarkets | C35: Store | D35: 29 Church St, Mafoluku Oshodi, Lagos 102214, Lagos, Nigeria | E35: +2348044080893
A36: Ado Guest House | B36: Hotels | C36: Guest house | D36: Oloruntoyin St, Somolu, Lagos 102216, Lagos, Nigeria
A37: Afaha and Afaha Investment | B37: Real Estate | C37: Real estate agency | D37: Oshodi, Lagos 100261, Lagos, Nigeria | E37: +2348033907736 | F37: https://www.facebook.com/share/1BNPYnrNBR/ | G37: 5 | H37: 1
A38: Affordable Properties | B38: Real Estate | C38: Real estate consultant | D38: Sura Mogaji St, Ilupeju, Lagos 100252, Lagos, Nigeria | E38: +2347038319834 | G38: 5 | H38: 4
A39: AFUS REAL ESTATE SERVICES LTD | B39: Real Estate | C39: Real estate consultant | D39: Odi-olowo, 16 Kolawole Shonibare St, Ilupeju, Lagos 100252, Lagos, Nigeria | E39: +2348036210138
A40: Aikson Global Associates Limited | B40: Professional Services | C40: Digital printing service | D40: 1, Ajose Adeogun close, off Oyefeso Ave, Obanikoro, Lagos 100232, Lagos, Nigeria | E40: +2348033439963 | F40: http://www.aiksonglobal.com/ | G40: 4.7 | H40: 10
A41: Air Liquide Nigeria Plc | B41: Pharmacies | C41: Pharmacy | D41: 84 Ladipo St, Mushin, Lagos 102215, Lagos, Nigeria | G41: 4.3 | H41: 50
A42: Airport Golden Tulip Hotel | B42: Hotels | C42: Hotel | D42: Airport Golden Tulip Hotel Lagos, 40–42 Airport Rd, opposite Ibis Hotel Royale, Ajao Estate, Ikeja 102214, Lagos, Nigeria | E42: +2348157003333 | F42: https://airportgoldentuliphotel.com/ | G42: 4.1 | H42: 692
A43: AJ salon | B43: Salons | C43: Hair salon | D43: Shop 75 ojo street, mushin, Lagos 300001, Lagos, Nigeria | E43: +2348154610351 | G43: 4 | H43: 2
A44: Ajerem properties | B44: Real Estate | C44: Commercial real estate agency | D44: 215-219 Olabode house obanikoro illupeju lagos, Mushin, Ikeja 100001, Lagos, Nigeria | E44: +2348155055276 | G44: 5 | H44: 1
A45: Ajitech Electrical Engineering Limited | B45: Home Services | C45: Electrician | D45: 10, 33 Micheal St, Ojuolobun Street, Victoria Island, Lagos 102214, Lagos, Nigeria | E45: +2348168036108
A46: Ajoke A.K And Beauty Salon | B46: Auto Services | C46: Parking garage | D46: 7 Peluola St, Oworosoki, Lagos 105102, Lagos, Nigeria | E46: +2348020927268
A47: Akara Ogheneworo Photograph | B47: Event Businesses | C47: Photographer | D47: 17 Esther Oshiyemi St, Ilupeju, Lagos 102215, Lagos, Nigeria
A48: Akefada International Ltd | B48: Real Estate | C48: Real estate consultant | D48: 248 Ikorodu Rd, Obanikoro, Lagos 102216, Lagos, Nigeria | E48: +2349026669981 | F48: http://www.akefadainternational.com/ | G48: 5 | H48: 2
A49: Akintola Williams Deloitte | B49: Professional Services | C49: Business center | D49: Akintola Williams Deloitte House, 235 Ikorodu Rd, Ilupeju, Lagos 102215, Lagos, Nigeria | F49: https://www2.deloitte.com/ | G49: 4.4 | H49: 24
A50: Akonji S Supermarket | B50: Supermarkets | C50: Supermarket | D50: New Garage, 1 Alarape St, Bariga, Lagos 102216, Lagos, Nigeria | E50: +2348034945917
A51: Al - Irshad Nursery and Primary School | B51: Schools | C51: Elementary school | D51: 29 Akinwunmi St, Gbagada, Lagos 105102, Lagos, Nigeria
A52: Alan King 1875 | B52: Real Estate | C52: Real estate consultant | D52: 274 Ikorodu Rd, Obanikoro, Lagos 102216, Lagos, Nigeria | E52: +2348023164277 | F52: http://alanking1875.com/ | G52: 5 | H52: 3
A53: Alaro guest house | B53: Hotels | C53: Campground | D53: Ali, off, olojojo bus stop, No 15, Oworonshoki, Lagos, Nigeria | E53: +2347016954422 | G53: 2 | H53: 1
A54: Alayo Beauty Salon | B54: Salons | C54: Beauty salon | D54: Off Alayaki Street, Mushin, 89 Olateju St, Lagos, Nigeria | E54: +2348187472344
A55: Aldamak Nouran Secondary School | B55: Schools | C55: High school | D55: 9 Alarape St, Abule Okuta, Lekki 106104, Lagos, Nigeria | E55: +2348145251485
A56: Alextino auto care services enterprise | B56: Supermarkets | C56: Car accessories store | D56: ihuoma plaza, 117 Ladipo St, Mushin, Papa 100253, Lagos, Nigeria | E56: +2348136998645 | G56: 5 | H56: 2
A57: Alhaji Jide Limited | B57: Home Services | C57: Plumber | D57: Off Shokunbi Street, 9 Olorunnisola St, Mushin, Lagos, Nigeria | E57: +2348163941446
A58: Alice's African Restaurant | B58: Restaurants | C58: Restaurant | D58: H84V+2G5, Orile Oshodi, Lagos 102214, Lagos, Nigeria | G58: 5 | H58: 3
A59: ALL PRINT | Graphic Design | Printing And Branding In Lagos, Nigeria. | B59: Professional Services | C59: Digital printing service | D59: 12 Ore-Ofero St, somolu, Lagos 102216, Lagos, Nigeria | E59: +2348101638842 | G59: 5 | H59: 19
A60: Allamyne Pharmacy | B60: Pharmacies | C60: Pharmacy | D60: G9XV+57F, Ashimowu St, Abule Okuta, Lagos 102216, Lagos, Nigeria | G60: 4.7 | H60: 3
A61: Alowonle Jedi Spot | B61: Restaurants | C61: Cafe | D61: H93V+4XX, Olaleye St, Gbagada, Lagos 105102, Lagos, Nigeria | G61: 3.9 | H61: 69
A62: Alpha & Partners | B62: Professional Services | C62: Law firm | D62: 19, Town Planning Way, 1st Floor (Right Wing, Ilupeju, Lagos, Nigeria | F62: https://alphaandpartners.com.ng/ | G62: 5 | H62: 1
A63: Alpha Plus Print Solutions | B63: Professional Services | C63: Digital printing service | D63: Local Government, 74 Ladipo St, off Chicken George Bus-Stop, Mushin, Lagos 100253, Lagos, Nigeria | E63: +2347065023542 | G63: 4.8 | H63: 41
A64: Alphrem & Co. | B64: Real Estate | C64: Real estate consultant | D64: 13 Association Ave, Ilupeju, Lagos 102215, Lagos, Nigeria | E64: +2349052289015 | G64: 3 | H64: 1
A65: Altruistic | B65: Boutiques | C65: Computer service | D65: 2nd floor, underbridge b/stop, left wing shops, 14 Oshodi Rd, beside first bank plc kairo market, oshodi, Lagos 100261, Nigeria
A66: Amaco auto | B66: Auto Services | C66: Auto body shop | D66: 28 Osoro St, ladipo road, Mushin, Lagos 100253, Lagos, Nigeria | E66: +2349065291647
A67: Amanda Asagba | B67: Professional Services | C67: Attorney | D67: 19 Town Planning Way, Ilupeju, Lagos 102215, Lagos, Nigeria | E67: +2348035353306
A68: Amatex Paradise Guest House | B68: Hotels | C68: Guest house | D68: 8Jagunmolu Street, Somolu, Lagos 102216, Lagos, Nigeria
A69: Amazing Eagle Hair Salon | B69: Salons | C69: Hair salon | D69: 9,Oke Owo Crescent, Olambe Rd, Ifo, Ogun State, Nigeria | E69: +2348108161508
A70: Amberstone Children School | B70: Schools | C70: Educational institution | D70: 14, Olayinka Street, Off Olaleye Street, Sawmill Ifako Gbagada, Lagos, Nigeria., 10, Gbagada, Lagos, Nigeria | E70: +2348060065646 | G70: 5 | H70: 3
A71: Amicreatives Photography Studio | B71: Event Businesses | C71: Photography studio | D71: 3 Bello Cresent, Ilupeju, Lagos 102215, Lagos, Nigeria | E71: +2348023866483 | G71: 4 | H71: 1
A72: Amos & Bros. Nigeria Ltd | B72: Home Services | C72: Electrician | D72: Oshodi Main Market, Oshodi pedestrian Overpass, Oshodi, Ikeja 102214, Lagos, Nigeria | E72: +2348093467259
A73: Anchorwin Pharmacy | B73: Pharmacies | C73: Pharmacy | D73: 19,Ankpa Quarters, Ado, Lagos, Nigeria | E73: +2347039842470
A74: Angels Nail Studio | B74: Salons | C74: Nail salon | D74: 20 Mafoluku Rd, Oshodi, Ikeja 102214, Lagos, Nigeria | E74: +2348030430731
A75: ANNY HAIR BEAUTY SALON | B75: Salons | C75: Hair salon | D75: 12A Abiodun odeseye Harmony Estate Ifako Lagos 12A, Abiodun Odeseye Street Harmony Estate Ifako Gbagada. Ifako, Gbagada, 100001, Lagos, Nigeria | E75: +2348023947328 | G75: 4.9 | H75: 21
A76: Anuoluwapo Catering And Hotel Management | B76: Caterers | C76: Caterer | D76: 1 Tinubu Cl, Ilupeju, Lagos 102215, Lagos, Nigeria | E76: +2348097304567
A77: Apelehin post office | C77: Post office | D77: Diya St, Abule Okuta, Lagos 102216, Lagos, Nigeria | G77: 3 | H77: 2
A78: Aphamed Prints Ltd | B78: Professional Services | C78: Digital printing service | D78: market, 9 Alabi St, off Adaranijo Street, Pedro, Lagos 100232, Lagos, Nigeria | E78: +2347013972790 | F78: http://aphamed.com/ | G78: 5 | H78: 21
A79: Apostolic faith church, oworo parish | B79: Churches | C79: Apostolic church | D79: 8 Ade Sheke St, Oworosoki, Lagos 105102, Lagos, Nigeria | G79: 3.8 | H79: 4
A80: Aqua Day Spa | B80: Salons | C80: Spa | D80: 54-64 Lanre Awolokun St, Somolu, Lagos 102216, Lagos, Nigeria | E80: +2348084683544 | G80: 2 | H80: 2
A81: Aquila Nidus Montessori School | B81: Schools | C81: Preschool | D81: Harmony Estate Ifako, 18 Ashafa Tijani St, Gbagada, Lagos 100242, Lagos, Nigeria | E81: +2347081864078 | G81: 4.5 | H81: 15
A82: Araromi Food Canteen | B82: Restaurants | C82: Restaurant | D82: 62 Shotinoye St, Papa Ajao, Lagos 100253, Lagos, Nigeria | G82: 3.6 | H82: 109
A83: Artistic Plus | B83: Event Businesses | C83: Event planner | D83: 13 Alhaji Salahu street, sitaaga, Ibadan 200129, Lagos, Nigeria | E83: +2348038682537
A84: AskMrInsure | Best Insurance Agency In Lagos Nigeria | Insurance Agent s Near Me (You) | Professional Insurance Agency. | B84: Professional Services | C84: Insurance agency | D84: Mile 7 Ikorodu Rd, Obanikoro, Lagos 100242, Lagos, Nigeria | E84: +2347084000022 | G84: 4.9 | H84: 26
A85: Assizes Lawfirm | B85: Professional Services | C85: Legal services | D85: 10 Ayodele Ojo St, Ilupeju, Lagos 100252, Lagos, Nigeria | E85: +2348033412508 | G85: 5 | H85: 2
A86: Astranad Pharmacy & Store | B86: Pharmacies | C86: Pharmacy | D86: G9P4+423, Fafolu St, Mushin, Lagos 102215, Lagos, Nigeria | E86: +2348126486707 | G86: 4.4 | H86: 5
A87: Atirira | B87: Professional Services | C87: Digital printing service | D87: 11b Taiwo Koya St, Ilupeju, Lagos 102215, Lagos, Nigeria | E87: +2347040209218 | F87: https://www.atirira.com/ | G87: 5 | H87: 1
A88: Aunty Kenny Provision Store | B88: Supermarkets | C88: General store | D88: 48 Owoseni St, Mafoluku Oshodi, Lagos 102214, Lagos, Nigeria | E88: +2347041490552
A89: Auto Body Workshop | B89: Auto Services | C89: Auto body shop | D89: 38 Ilupeju Industrial Ave, Mushin, Lagos 102215, Lagos, Nigeria | G89: 5 | H89: 1
A90: Auto parts store | B90: Supermarkets | C90: Auto parts store | D90: 46 Osoro St, Mushin, Lagos 102215, Lagos, Nigeria | E90: +2348082581141 | G90: 4 | H90: 1
A91: Auto Spare Parts | B91: Auto Services | C91: Auto body parts supplier | D91: Osoro St, Mushin, Lagos 102215, Lagos, Nigeria | E91: +2347048221992
A92: Auto Spare Parts Motor | B92: Auto Services | C92: Motor vehicle dealer | D92: 23/24 Block C Auto Spare Parts Motor, Ladipo St, Lagos, Nigeria | E92: +2347042165377 | F92: http://www.motorspareparts.com/ | G92: 4.4 | H92: 11
A93: Autocare Diagnostics Nigeria Enterprise | B93: Auto Services | C93: Auto repair shop | D93: 8 Olutunda St, Ilupeju, Lagos 102215, Lagos, Nigeria | E93: +2348181982545
A94: Autogig International Resources Limited | B94: Auto Services | C94: Auto repair shop | D94: 144b Gbagada - Oworonshoki Expy, Pedro, Lagos 102216, Lagos, Nigeria | E94: +2348178793634 | G94: 4.5 | H94: 68
A95: Automedics limited | B95: Auto Services | C95: Car repair and maintenance service | D95: Ilupeju Byepass, Onipanu, Lagos 100252, Lagos, Nigeria | E95: +2348095718075 | F95: https://automedicsafrica.com/ | G95: 4 | H95: 178
A96: AUTOMOB ADVISORY SERVICES | B96: Auto Services | C96: Auto repair shop | D96: 29 Adewale Cres, Apapa-Oshodi Express Way, off Kunle Akinosi, Isolo, Lagos 102214, Lagos, Nigeria | E96: +2348090547576
A97: Autoulicas International Limited | B97: Auto Services | C97: Auto repair shop | D97: Promise Land Lagos, 1-5 Jimade CLose, Ladipo St, Lagos, Nigeria | E97: +2347031804073
A98: Aventura Photography | B98: Event Businesses | C98: Photographer | D98: 258 Ikorodu Rd, Obanikoro, Lagos 300001, Lagos, Nigeria | E98: +2348136647730
A99: Awesome Bezalel Event | B99: Event Businesses | C99: Event management company | D99: 86 Shipeolu street Palmgrove, Palmgrove, Lagos 100231, Lagos, Nigeria | E99: +2348023554754 | F99: http://www.instagram.com/awesomebezalelevent | G99: 5 | H99: 1
A100: Awoof Berekete (Obanikoro) | B100: Restaurants | C100: Restaurant | D100: 250 Ikorodu Rd, Obanikoro, Lagos 100232, Lagos, Nigeria | E100: +2348082796358 | G100: 4.3 | H100: 1405
A101: AY Fitness Centre | B101: Gyms | C101: Gym | D101: 3 Okulaja St, Orege, Lagos 102216, Lagos, Nigeria | E101: +2347064443280 | G101: 2.7 | H101: 6
...
